{
    "welcome": {
        "choose_lang": "Elige tu idioma",
        "next": "Siguiente",
        "back": "Atrás",
        "submit": "Entregar",
        "set_pwd": "Configurar la contraseña de Adiminstración",
        "new_pwd": "Nueva contraseña",
        "new_pwd_placeholder": "Introducir la contraseña",
        "confirm_pwd": "Confirmar la contraseña",
        "confirm_pwd_placeholder": "Las contraseñas no coinciden",
        "unknown_err_msg": "El Wi-Fi se apaga durante la inicialización del router, por favor compruebe que su dispositivo cliente se ha vuelto a conectar al router.",
        "htmode_160_label": "Ancho de Banda dinámico de 160 Mhz",
        "welcome_slogan": "Bienvenidos a GL.iNet!",
        "set_wifi_title": "Configurar la red Wi-Fi",
        "htmode_160_tips": "El ancho de banda de 160 Mhz ofrece tanto un mayor rendimiento como un mejor cubrimiento. Si se activa esta función, es necesario esperar 60 segundos para que el enrutador detecte si hay señales de radar y así evitar problemas de interferencia.",
        "wifi_restart_loading_text": "Puede tomar algunos segundos, por favor esperar.",
        "pwd_inconsistencies": "Inconsistencias en la clave de seguridad",
        "reconnected_wifi_loading_text": "Asegúrese de que el enrutador se ha re-conectado a la siguiente red Wi-Fi."
    }
}
