{
    "vpn": {
        "ovpn_desc": "OpenVPN은 가상 사설망(OpenVPN) 기술을 구현하여 라우팅 또는 브리지 구성과 원격 액세스 기능에서 지점 간 또는 사이트 간 안전한 연결을 생성하는 오픈 소스 소프트웨어 애플리케이션입니다. 아래 단계를 따르십시오.",
        "ovpn_step_tip1": "1. OpenVPN 구성 파일을 생성합니다;",
        "ovpn_step_tip2": "2. 기본 구성을 수정한 후 저장합니다;",
        "ovpn_step_tip4": "4. VPN 대시보드 페이지로 이동하여 VPN 서버를 시작합니다.",
        "ovpn_step_tip3": "3. 클라이언트 구성 파일을 내보내기(다운로드) 합니다;",
        "custom_route_desc": "각 VPN 클라이언트에 대한 라우팅 규칙을 수동으로 구성할 수 있습니다.",
        "wg_step_tip1": "1. WireGuard® 구성 파일을 생성합니다.",
        "ovpn_tips": "아직 OpenVPN 구성 파일이 없습니다. 시작하려면 구성 설정을 생성하세요.",
        "wg_desc": "WireGuard®는 최신 암호화를 활용하는 매우 간단하고 빠르며 현대적인 VPN입니다. 아래 단계를 따르십시오:",
        "autodetec_desc": "각 VPN 클라이언트 구성 파일에 정의되거나 VPN 서버에서 구성된 라우팅 규칙이 사용됩니다.",
        "custom_route": "아직 peer 구성이 없습니다. 시작하려면 peer 구성을 추가하세요",
        "choose_config_file_tips": "클라이언트가 실행되는 동안 구성 파일을 전환할 수 있습니다. 구성 파일을 전환하는 과정에서 트래픽 노출이 발생하지 않습니다.",
        "tunnel_ip": "터널 주소",
        "client_vpn_private_ip": "클라이언트 가상 IP",
        "vpn_private_ip": "가상 IP",
        "public_ip": "실제 IP",
        "server_location": "서버 위치",
        "allowed_ip": "허용된 IP",
        "wg_step_tip2": "2. 피어 구성을 추가합니다;",
        "wg_step_tip3": "3. 피어 정보를 클라이언트에 복사합니다;",
        "wg_tips1": "아직 피어 구성이 없습니다. 시작하려면 피어 구성을 추가하세요.",
        "server": "서버",
        "modify_proxy_mode": "프록시 모드 변경",
        "autodetec": "자동 감지",
        "wg_step_tip4": "4. VPN 대시보드 페이지로 이동하여 VPN 서버를 시작합니다.",
        "client": "클라이언트"
    }
}
