{
    "tailscale": {
        "current_ip_tips": "",
        "enable_wan_label": "",
        "exit_node_label": "",
        "custom_exit_node_tips": "",
        "manual_node_label": "",
        "custom_exit_node_warning": "",
        "dns_warning_tips": "",
        "allow_wan_tips": "",
        "allow_lan_tips": "",
        "ready_tips": "",
        "logout_btn": "",
        "current_ip_label": "",
        "need_mandate_tips": "",
        "enable_lan_label": "",
        "account_label": "",
        "get_url_err_msg": "",
        "exit_node_tips": "",
        "need_login_tips": "",
        "enable_lan_tips": "",
        "desc": ""
    }
}
