{
    "adminpw": {
        "old_pwd": "旧密码",
        "new_pwd": "新密码",
        "confirm_pwd": "确认新密码",
        "warning": "不能与旧密码相同",
        "confirm_pwd_tips": "再次输入新密码",
        "password_tips": "至少需要 $$$$ 位，至多 $$$$ 位",
        "allow_password_tips": "可以输入字母（区分大小写）、数字及符号 $$$$",
        "security_password_tips": "至少需要大写字母、小写字母、数字、符号其中的两项",
        "not_allow_weak": "不允许使用弱密码",
        "use_weak_tips": "使用弱口令是不安全的行为，弱口令总是在黑客攻击中扮演重要角色。如果密码的强度非常低，攻击者会很容易猜中它或完成暴力破解。"
    },
    "menu_adminpw": "管理员密码"
}
