{
    "login": {
        "login": "Login",
        "admin_password": "Password di Amministratore",
        "password_hint": {
            "placeholder": "Si prega di inserire la password",
            "null": "ATTENZIONE: Non può essere vuoto!"
        },
        "forgot_password": {
            "title": "Ho dimenticato la Password",
            "desc": "Prova a tenere premuto il tasto \"riavvio\" per 10 secondi, quindi rilascialo. Vedrai la luce LED lampeggiare. Attendi il riavvio del router e poi configuralo da capo.",
            "online_docs": "Documentazione online",
            "screen_check_admin_password_tips": "请检查设备屏幕上的管理员密码。如果您忘记了密码，请按照以下步骤操作。"
        },
        "err_msg": "L'username o la password non sono corretti!",
        "retry_after": "Hai provato ad accedere troppe volte, riprova tra $$$$ secondi."
    }
}
