{
    "macclone": {
        "factory_default_label": "Fabrieksinstellingen",
        "clone_label": "Klonen",
        "manual_label": "Handmatig",
        "mode_label": "Modus",
        "current_client_label": "Huidig apparaat",
        "random_btn": "Willekeurig",
        "no_mac_tips": "Laten generen wanneer de netwerkpoort wordt ingeschakeld",
        "desc": "Als u verbinding maakt met een openbare hotspot, maar niet wilt dat de server uw echte MAC-adres kent of uw internetverbindingen beperkt op basis van uw MAC-adres.",
        "tips": "Als uw hotel of andere bedrijfslocaties netwerkverificatie vereisen, kan het klonen van MAC-adressen helpen."
    },
    "menu_macclone": "MAC-adres"
}
