{
    "macclone": {
        "current_client_label": "Mevcut İstemci",
        "random_btn": "Rastgele",
        "no_mac_tips": "Arayüz etkinleştirildiğinde oluşturuldu",
        "desc": "Genel bir ağa (örn. otel/AVM) bağlandığınızda, ağ yöneticisinin gerçek MAC adresinizi bilmesini istemiyorsanız veya İnternet erişiminizi buna göre sınırlamak istemiyorsanız rastgele bir MAC adresi kullanın.",
        "tips": "Oteliniz veya diğer iş yerlerinizin ağı kimlik doğrulama gerektiriyorsa, MAC kopyalama kullanmanız gerekebilir.",
        "factory_default_label": "Fabrika Varsayılanları",
        "clone_label": "Klonla",
        "manual_label": "Manuel",
        "mode_label": "Mod",
        "current_interface_as_lan_tips": "Mevcut arayüz bir LAN portudur. Yapılandırma, WAN portuna geçildiğinde etkili olacaktır."
    },
    "menu_macclone": "MAC Adresi"
}
