{
    "cable": {
        "title": "이더넷",
        "no_wan": "WAN 포트에 케이블이 감지되지 않았습니다. 이더넷 케이블을 연결하세요.",
        "rm_wan_cable": "WAN 포트에서 이더넷 케이블을 분리해 주세요.",
        "confirm_to_wan": "LAN 포트를 다시 WAN으로 변경하시겠습니까?",
        "wan_been_lan": "WAN 포트가 LAN으로 사용되었습니다. 아래에서 WAN으로 다시 설정할 수 있습니다",
        "confirm_to_lan": "WAN 포트를 LAN으로 사용하시겠습니까?",
        "using_as_lan": "LAN으로 사용 중, $$$$ WAN으로 변경$$$$",
        "repeated": "재연결할 필요 없이 성공적으로 연결됨",
        "pppoe_log": "PPPoE 접속 기록",
        "using_as_wan": "WAN으로 사용, $$$$ LAN으로 변경하기$$$$",
        "change_to_lan_check_tips": "먼저 WAN 포트에 연결된 이더넷 케이블을 분리하세요. $$$$ 다시 감지 $$$$",
        "egderouter_mode_tips": "드롭인 게이트웨이가 활성화되었습니다. 이더넷 설정을 수정하려면 먼저 $$$$ 드롭인 게이트웨이$$$$ 를 비활성화하세요.",
        "change_to_wan_tips": "LAN 포트가 WAN 포트로 사용되면 LAN 포트에 연결된 이 이더넷 포트를 통해 관리자 패널에 액세스할 수 없습니다. 클라이언트가 Wi-Fi 또는 다른 LAN 포트에 연결할 수 있는지 확인하세요.",
        "change_to_wan_tips2": "장치의 재설정 버튼을 4초간 길게 누르면 LAN 포트를 복원(더 이상 WAN 포트로 사용되지 않도록)할 수 있습니다.",
        "setting": "이더넷 설정",
        "dhcp_tips": "IP 주소는 상위 네트워크 기기에 의해 할당됩니다.",
        "pppoe_vlanid_tips": "이 설정 항목은 공급자의 PPPoE 서버에서 인터페이스에 태그가 지정된 특정 VLAN ID를 사용하도록 요구하는 경우에만 필요합니다.",
        "reset_port_tips": "기기의 리셋 버튼을 4초간 누르고 있으면 {silkprint}를 복원할 수 있습니다.",
        "use_as_wan_tips": "{asWan}에 연결된 장치는 더 이상 관리자 패널에 접근할 수 없습니다. Wi-Fi 또는 다른 LAN 포트에 연결해야 합니다.",
        "use_as_port_btn": "{silkprint}을 {port}(으)로 변경",
        "revert_as_lan_tips": "{silkprint}을 LAN 포트(기본값)로 복원하시겠습니까?",
        "use_as_wan_silkprint_tips": "{silkprint}이 WAN 포트로 사용되면",
        "using_tips": "{silkprint} 상태: {port}로 사용 중. {changePort}",
        "change_port_btn": "{port}로 변경",
        "revert_port_btn": "{port}로 복원",
        "revert_wan_tips": "WAN 포트를 복원한 후에",
        "no_wan_tips": "케이블이 감지되지 않았습니다.",
        "vlan_id_conflict_tips": "Ethernet1 VLAN ID가 Ethernet2 VLAN ID와 충돌합니다."
    },
    "tethering": {
        "title": "테더링",
        "device": "장치",
        "no_device_tips": "테더링 장치를 찾을 수 없습니다. 시작하려면 스마트폰이나 USB 모뎀을 연결하세요."
    },
    "repeater": {
        "no_tips": "중계기(STA)가 비활성화되어 있습니다.",
        "join_wifi": "Wi-Fi 연결",
        "join_title": "네트워크에 연결",
        "join_other": "다른 네트워크에 연결",
        "ssid": "SSID",
        "encryption": "보안",
        "identity": "사용자명",
        "key": "비밀번호",
        "remember": "기억해 두세요",
        "lock_bssid": "BSSID 잠금",
        "advanced_settings": "고급 설정",
        "allow_dfs": "DFS 채널 반복 허용",
        "allow_dfs_tips2": "이 옵션을 비활성화하면 라우터는 DFS 채널을 사용하여 Wi-Fi에 연결하지 않습니다.",
        "retry_disable_guest_tips": "재연결을 시도하는 동안 라우터는 주기적으로 Wi-Fi 네트워크를 검색하며, 이 검색 중에 게스트 Wi-Fi 네트워크를 일시적으로 사용할 수 없게 됩니다.",
        "scan_disable_guest_tips": "Wi-Fi 신호를 검색하는 동안 약 10초 동안 게스트 네트워크를 일시적으로 사용할 수 없습니다. 계속하시겠습니까?",
        "fail_eap_key_tips": "사용자 이름 또는 비밀번호가 잘못되었습니다.",
        "fail_key_tips": "잘못된 비밀번호입니다.",
        "fail_not_found_tips": "네트워크를 찾을 수 없습니다. 입력한 SSID와 보안 유형을 확인하세요.",
        "unusable_eap_tips": "이 라우터는 EAP를 사용하는 반복 네트워크는 지원하지 않습니다.",
        "fail_mac_tips": "라우터의 MAC 주소는 다른 Wi-Fi 클라이언트와 동일할 수 없으므로 $$$$클론의 MAC을 수정하세요$$$$ 또는 해당 클라이언트의 MAC 주소를 수정하세요.",
        "title": "중계기",
        "known_net": "알려진 네트워크",
        "options": "중계기 옵션",
        "change_wifi": "네트워크 스위치",
        "allow_change": "저장된 다른 네트워크로 전환 허용",
        "allow_change_tips": "이 옵션을 활성화하면 라우터가 현재 Wi-Fi 네트워크에 연결할 수 없을 때 저장된 다른 네트워크에 자동으로 연결됩니다.",
        "antijam": "2.4G 대역폭을 20MHz로 강제 설정",
        "antijam_tips": "이 옵션을 활성화하면 장치가 연결 속도를 줄여 연결 안정성을 개선합니다.",
        "lock_band": "대역 선택",
        "lock_band_tips": "수동으로 대역을 선택하면 라우터는 다른 대역을 사용 중인 Wi-Fi를 검색하거나 연결하지 않습니다.",
        "detail_title": "네트워크 세부 정보",
        "available_wifi": "사용할 수 있는 네트워크",
        "set_static": "고정 IP 수동 설정하기",
        "unlock": "자동",
        "antijam_tips_2": "2.4G Wi-Fi를 반복해서 사용할 때만 작동합니다.",
        "retry_connet_tips": "연결에 실패했습니다, 나중에 다시 시도하겠습니다…",
        "lock_bssid_tips": "이 옵션을 활성화하면 라우터는 이 SSID를 사용하는 네트워크로 전환할 때 선택한 BSSID에 해당하는 AP에만 연결합니다.",
        "allow_dfs_tips1": "이 옵션을 활성화하면 라우터가 DFS 채널에서 Wi-Fi를 반복할 때 DFS 채널 회피를 위해 핫스팟을 따릅니다. 이 Wi-Fi를 사용할 수 있는 경우 라우터 자체의 5GHz Wi-Fi가 DFS 채널을 사용합니다. 그렇지 않으면 라우터 자체의 5GHz Wi-Fi가 비-DFS 채널로 다시 전환됩니다.",
        "scan_wifi_fail_dfs_tips": "장치가 DFS 채널 가용성 검사를 실행 중이며 근처 Wi-Fi를 검색할 수 없습니다. 검사가 완료될 때까지 기다려 주세요.",
        "connet_dfs_tips": "라우터가 DFS 채널이 있는 Wi-Fi를 반복할 때, 이 Wi-Fi를 사용할 수 있는 경우 라우터는 선택한 DFS 채널을 사용합니다. 이 WiFi를 사용할 수 없는 경우 채널이 전환되어 WiFi를 통해 연결된 클라이언트의 연결이 잠시 끊어지고, 일부 장치는 감지 없이 재연결되는 반면 일부 장치는 수동으로 재연결해야 합니다.",
        "cannot_accessed_portal_url_tips": "로그인 페이지에 접속할 수 없는 경우, 다른 인터넷 연결(예: 이더넷, 셀룰러)을 비활성화해 보세요.",
        "quit_btn": "로그인 모드 종료",
        "allow_auto_portal_label": "공공 핫스팟용 로그인 모드 자동 활성화",
        "modify_wifi_title": "네트워크 설정 수정",
        "enable_disguise_label": "위장 기능 활성화",
        "auto_go_auth_tips": "자동으로 {auth} 후 {count}",
        "modify_wifi_tips": "네트워크 설정 변경으로 리피터가 재연결됩니다.",
        "going_to_auth_tips": "로그인 페이지로 리다이렉트 중:",
        "to_auth_btn": "로그인으로 이동",
        "portal_auth_mode_btn": "공공 핫스팟을 위한 로그인 모드",
        "auto_portal_tips": "장치가 Captive Portal의 핫스팟에 접속하기 위해 공용 핫스팟 로그인 모드로 진입했습니다. 로그인에 성공하면 자동으로 이 모드를 벗어납니다.",
        "enable_disguise_tips": "이 옵션을 활성화하면, 이 라우터는 현재 사용 중인 클라이언트 기기와 동일한 기기로 위장합니다.",
        "entry_again_tips": "10초 이내에 다시 입력하면 재스캔하는 대신 캐시를 직접 불러옵니다.",
        "scan_wifi_fail_detection_channel_tips": "장치가 최적의 채널을 스캔 중입니다. 이 과정에서 Wi-Fi 스캔을 사용할 수 없습니다. 스캔이 완료될 때까지 기다려 주십시오.",
        "cannot_find_ssid": "SSID를 찾을 수 없습니까?",
        "allow_auto_portal_tips": "이 옵션을 활성화하면, 라우터가 핫스팟에는 연결되었지만 인터넷에는 연결되지 않은 경우 자동으로 공용 핫스팟 로그인 모드로 전환됩니다. 이 모드에서는 일부 서비스가 중단되며 DNS 모드가 자동으로 전환되어 네트워크 활동 정보가 핫스팟 제공업체(예: 호텔 또는 쇼핑몰)에 유출될 수 있습니다.",
        "need_enter_portal_tips": "통해 인터넷에 접속할 수 없습니다. {portal}에 들어가 문제를 해결해 보세요. 이 모드는 일부 서비스와 사용자 지정 DNS를 일시 중지할 것이며, 이로 인해 핫스팟 제공자(예: 호텔/쇼핑몰)에게 데이터 유출이 발생할 수 있습니다.",
        "entered_portal_tips": "이 장치는 공공 핫스팟을 위한 로그인 모드에 있습니다. 일부 서비스가 일시 중지되어 핫스팟 제공자(예: 호텔/쇼핑몰)에게 데이터 유출이 발생할 수 있습니다. 로그인에 성공하면 이 라우터는 자동으로 이 모드를 종료합니다. {exit}.",
        "router_support_channel_tips": "SSID 작동 채널을 확인하십시오. 이 라우터는 지원합니다:",
        "channel": "{band} 채널",
        "cannot_find_wifi": "내 Wi-Fi를 찾을 수 없습니다?",
        "ssid_not_hidden_tips": "SSID가 숨겨져 있지 않은지 확인하십시오.",
        "make_sure_works_tips": "모바일 폰으로 시도해 보시고 정상 작동하는지 확인해 주세요.",
        "support_tips": "문의사항이 있으시면 {addr}로 연락주시기 바랍니다.",
        "allow_other_mode_change": "다른 네트워크 모드로 전환 허용",
        "no_switching": "전환 없음",
        "auto_switching": "自动切换",
        "auto_switching_without_network": "네트워크 없이 자동 전환",
        "no_switching_tips": "전환 모드가 비활성화되면 현재 Wi-Fi 연결이 끊어졌을 때 다른 저장된 네트워크에 연결되지 않습니다.",
        "auto_switching_tips": "자동 전환 모드가 활성화되면 현재 Wi-Fi 연결이 끊어지면 다른 저장된 네트워크에 연결됩니다.",
        "repeater_not_auto_scan_tips": "현재 {mode} 모드가 활성화되어 있습니다. 라우터가 비반복기 모드에서 인터넷에 성공적으로 연결되면, 반복기는 자동으로 네트워크 스캔을 수행하지 않습니다.",
        "portal_go_to_auth_page_tips": "{ssid}에 연결되었습니다. 인터넷 접속을 위해 인증 페이지에서 로그인해 주세요.",
        "regionally_allowed_channel_tips": "이 라우터는 현재 지역에서 허용된 Wi-Fi 채널 신호만 검색할 수 있습니다.",
        "tap_icon_tips": "아이콘을 클릭하여 Wi-Fi 채널 팁을 다시 표시합니다.",
        "portal_entered_bare_mode_tips": "이 장치는 공용 핫스팟을 위한 로그인 모드입니다. 로그인에 성공하면 이 라우터는 자동으로 이 모드를 종료합니다. {exit}",
        "portal_need_enter_bare_mode_tip": "이 Wi-Fi 핫스팟을 통해 인터넷에 접속할 수 없습니다. 인터넷 계속 사용을 원하시면 {portal}을 클릭하세요.",
        "portal_need_click_next_tips": "이 Wi-Fi 핫스팟을 통해 인터넷에 접속할 수 없습니다. \"{btn}\" 버튼을 클릭하여 공공 핫스팟 로그인 모드로 진입하여 인터넷 접속을 계속하세요.",
        "portal_show_disable_detail_btn": "이 모드에서 비활성화되는 기능에 대한 상세 정보",
        "portal_disable_vpn_tips": "동시에, 이 모드가 종료될 때까지 장치는 VPN 없이 트래픽을 라우팅하며, 이는 핫스팟 제공자(예: 호텔/쇼핑몰)에게 데이터가 유출될 수 있음을 의미합니다.",
        "portal_disable_feature_tips": "이 모드는 {feature}을(를) 자동으로 일시적으로 비활성화합니다.",
        "portal_auth_required_title": "포털 인증이 필요합니다.",
        "support_channel_tips": "다음 Wi-Fi 채널이 지원됩니다. 연결하려는 Wi-Fi 네트워크가 이 중 하나를 사용하는지 확인하세요.",
        "auto_switching_without_network_tips": "{mode} 모드가 활성화되면, 라우터는 비-리피터 모드에서 네트워크 연결에 성공했을 때 자동으로 네트워크를 스캔하지 않으며, 네트워크 연결이 끊겼을 때만 저장된 다른 네트워크로 자동 전환을 시도합니다. 이는 통신 패킷 손실을 방지할 수 있습니다.",
        "band_conflict_tips": "안정적인 연결을 위해 리피터가 활성화되면 게스트 Wi-Fi가 비활성화되고 5GHz/6GHz Wi-Fi 대역이 자동으로 리피터와 일치합니다. 기기가 자동으로 재연결되지 않으면 수동으로 Wi-Fi에 연결해 주세요.",
        "auto_resume_scan_tips": "인터넷이 연결되었습니다. 무선 통신 품질을 보장하기 위해 리피터는 사용 가능한 네트워크를 스캔하지 않으며, 인터넷 연결이 끊긴 후 자동으로 스캔을 재개합니다. 수동으로 Wi-Fi 네트워크에 재연결하거나 전환할 수 있습니다."
    },
    "modem": {
        "title": "셀룰러",
        "manage": "관리",
        "name": "모뎀명",
        "phone_num": "전화 번호",
        "operator": "모바일 네트워크 운영자",
        "upload": "업로드",
        "install_sim": "SIM 카드 설치",
        "reboot_this": "모뎀 재부팅",
        "port": "포트",
        "port_tips": "cdc-wcdm0 포트가 더 빠르며, ttyUSBX 포트는 호환성이 더 좋습니다.",
        "manually_tips": "수동 입력",
        "ttl_placeholder": "옵션, 기본값 64",
        "pin": "핀코드",
        "service": "서비스",
        "dial_num": "다이얼 번호",
        "password": "비밀번호",
        "sim_not_registered": "등록되지 않은 SIM 카드",
        "connect_fail_tips": "연결 실패, 다시 연결 중…",
        "manual_setup": "수동 설정",
        "auto_setup": "자동 설정",
        "setting": "셀룰러 환경 설정",
        "traffic": "트래픽 통계",
        "reset_count": "통계 지우기",
        "clear_traffic": "트래픽 통계 자동 저장 사용 안 함",
        "not_compatible": "호환되지 않는 모뎀",
        "connecting_tips": "일부 SIM 카드에는 특정 APN을 사용해야 하는 등 특별한 사용 제한이 있습니다. SIM 카드를 등록할 수 없는 경우, 네트워크 사업자에게 문의하여 사용 중인 SIM에 특별한 제한이 있는지 확인하세요.",
        "sim_slot_switching_tips": "SIM 카드 슬롯 전환 중…",
        "plug_in_tips": "모뎀 장치를 찾을 수 없습니다. 시작하려면 USB 모뎀을 연결하세요.",
        "signal": "신호",
        "download": "다운로드",
        "install_sim_tips": "SIM 카드를 SIM 슬롯에 삽입한 다음 다음과 같이 하세요",
        "apn_tips": "일부 SIM 카드에는 특정 APN이 필요합니다. 정확한 APN을 모르는 경우 네트워크 사업자에게 문의하세요.",
        "ttl_tips": "일부 네트워크 사업자는 TTL 값을 읽어 라우터에서 SIM 카드 사용 여부를 결정합니다. 라우터에서 SIM 카드를 사용할 수 없는 경우 TTL을 64와 128이 아닌 다른 값(예: 65)으로 설정해 볼 수 있습니다.",
        "authentication": "인증",
        "user_name": "사용자명",
        "sim_lock": "SIM 카드가 잠겼습니다. 잠금을 해제하려면 PIN 코드를 입력하세요.",
        "traffic_tips": "트래픽 통계는 정보 제공용이며, 실제 트래픽은 네트워크 사업자가 결정하며 네트워크 사업자가 제공하는 청구서에 표시됩니다.",
        "clear_traffic_tips": "이 옵션을 활성화하면 시스템이 트래픽 통계를 자동으로 저장하지 않습니다.",
        "no_sim_tips": "SIM 카드가 감지되지 않았습니다. 카드가 올바르게 삽입되었는지, 접촉부가 깨끗한지 확인하세요. 모뎀은 핫스왑 가능한 SIM 카드를 지원하지 않습니다. 부팅 후 SIM 카드를 다시 삽입한 경우 $$$$Reboot Modem$$$$ 또는 라우터를 재부팅하세요.",
        "current_sim_label": "활성 SIM 카드",
        "current_config_title": "현재 설정",
        "saved_config_title": "프로필 저장됨",
        "use_other_config_btn": "다른 설정 사용",
        "current_config_badge": "사용 중",
        "save_config_label": "설정 저장",
        "copy_config_btn": "복제 및 수정",
        "sim_slot_setting_title": "SIM 카드 슬롯 설정",
        "auto_switch_label": "자동 전환",
        "main_slot_label": "기본 설정 SIM 카드 슬롯",
        "sim_profile_label": "SIM {index} 설정",
        "sim_no_profile_warning": "설정이 선택되지 않은 경우 자동으로 구성됩니다.",
        "choose_other_profile_btn": "다른 설정",
        "sim_failover_interval_label": "장애 조치 주기",
        "timing_check_main_sim_label": "예약된 기본 슬롯 상태 확인",
        "check_main_sim_time_label": "시간 전환",
        "choose_current_slot_label": "SIM 카드",
        "remove_profile_warning": "프로필을 삭제하시겠습니까? 프로필을 삭제한 후에는 복구할 수 없습니다.",
        "set_detection_tips": "인터넷 상태는 $$$$Multi-WAN$$$$ 페이지의 설정과 동일한 방식으로 감지됩니다.",
        "data_roaming_label": "해외 데이터 로밍",
        "enable_band_filter_label": "대역 마스킹 활성화",
        "band_filter_mode_label": "마스킹 모드",
        "band_masking_label": "차단",
        "band_only_label": "열기",
        "band_only_tips": "\"개방\" 모드에서는 라우터가 해당 대역만 사용하고 다른 대역은 차단됩니다.",
        "band_masking_tips": "\"차단\" 모드에서 라우터는 다음 대역을 차단합니다.",
        "band_only_warning": "허용된 밴드 중 하나 이상을 선택해 주세요.",
        "current_badge_label": "현재 상태",
        "current_sim_badge_label": "Active: SIM {sim}",
        "excellent_singal_label": "우수함",
        "good_singal_label": "좋음",
        "fair_singal_label": "페어",
        "manage_profiles_btn": "프로필 관리",
        "setting_sim_title": "SIM 사용 설정",
        "select_profile_desc": "$$$$ 프로필을 선택하면 $$$$ 프로필의 내용을 SIM 카드에서 사용하는 설정으로 복사할 수 있습니다.",
        "save_as_profile_title": "프로필로 저장",
        "edit_profile_title": "프로필 변경",
        "add_new_profile_title": "새 프로필 만들기",
        "select_profile_title": "프로필 선택",
        "sim_not_setup_label": "설정 없음",
        "name_already_exist_tips": "이 이름이 이미 존재합니다.",
        "history_signal_title": "과거 신호 기록",
        "lock_tower_title": "잠금 타워",
        "available_tower_title": "사용 가능 타워",
        "device_may_not_b_tips": "셀룰러 인터페이스가 활성화된 경우 기기가 모든 기지국을 스캔하지 못할 수 있습니다.",
        "cellular_desc": "셀룰러 인터페이스가 다시 연결되어 잠긴 타워로 전환됩니다.",
        "sim_tower_title": "SIM {sim} 타워",
        "tower_locked_tips": "타워 잠김",
        "reboot_buildin_modem_btn": "내장 모뎀 재부팅",
        "lte_plus_tips": "일부 기기에서 4G+가 5G로 표시될 수 있습니다",
        "sim_slot_pin_mark_tips": "SIM 카드 슬롯은 표시가 되어 있으며 자동으로 전환할 수 없습니다.",
        "pin_verify_success_tips": "PIN 코드 인증이 완료되었습니다.",
        "need_pin_history_tips": "PIN 코드 {value}이 올바르지 않습니다. {count}가 남았습니다.",
        "pin_locked_no_history_tips": "SIM 카드가 잠겼습니다.",
        "pin_locked_history_tips": "PIM 코드 {value} 오류, SIM 카드가 잠겼습니다.",
        "certification_info_btn": "인증서 정보",
        "sim_failover_interval_tips": "장애 조치가 수행된 후에도 인터넷 연결을 사용할 수 없는 경우, 장치는 기본 설정 SIM 슬롯으로 다시 전환되고 이 간격이 지난 후에만 장애 조치가 다시 시도됩니다.",
        "timing_check_main_sim_tips": "이 옵션을 활성화하면 장치가 지정된 시간에 선호하는 SIM 슬롯으로 다시 전환하려고 시도합니다. 이 기능을 사용하면 인터넷 연결이 가능할 때 선호하는 SIM 슬롯으로 다시 전환할 수 있습니다.",
        "poor_singal_label": "나쁨",
        "no_sim_tips2": "SIM 카드가 감지되지 않았습니다. 카드가 올바르게 삽입되었는지, 접촉부가 깨끗한지 확인하세요.",
        "has_been_choose_profile_desc": "프로필 이름}의 내용을 복사했습니다. $$$$ 다른 프로필 복사$$$$",
        "locked_tower_tips": "잠긴 타워가 셀룰러 설정의 대역 마스킹 또는 APN 매개변수와 일치하지 않으면 셀룰러 인터페이스가 인터넷에 연결할 수 없습니다.",
        "scan_tower_msg": "몇 분 정도 소요될 수 있습니다. 잠시만 기다려주세요.",
        "reboot_buildin_modem_warning": "내장 모뎀을 재부팅하시겠습니까?",
        "need_pin_no_history_tips": "PIN 코드를 입력해야 하며 {count}번의 시도가 남았습니다.",
        "protocol_tips": "QCM/QMI 프로토콜은 더 빠르며 3G 프로토콜은 호환성이 더 좋습니다.",
        "last_pin_tips": "이 SIM 카드의 PIN 코드를 잠금 해제하기 위한 마지막 시도가 남아 있습니다. 만약 다시 실패한다면, PUK 코드를 사용하여 잠금을 해제해야 합니다. SIM 카드가 잠기는 것을 방지하기 위해, 기기는 다시 다이얼하지 않으므로 휴대폰을 사용하여 잠금을 해제해 주세요.",
        "need_pin_tips": "SIM 카드가 잠겨 있습니다. PIN 코드가 입력되었는지 또는 입력된 PIN 코드가 올바른지 확인해 주세요.",
        "region_code_label": "국가 / 지역 코드",
        "band_block_warning": "모든 대역을 차단하지 마세요.",
        "traffic_days_tips": "최대 일수는 현재 달의 실제 최대 일수 값을 취합니다.",
        "network_type": "네트워크 유형",
        "lock_pin_tips1": "{sim}이 잠겼습니다. {unlock}을 클릭하고 PIN을 입력하여 잠금을 해제하십시오.",
        "sim_unlock": "{sim} 잠금 해제",
        "lock_pin_tips2": "{sim1} 및 {sim2}가 잠겨 있습니다. 각 SIM을 잠금 해제하려면 {unlock1} 또는 {unlock2}를 클릭하고 해당 PIN을 입력하십시오.",
        "sim_card_switch": "SIM 카드 전환",
        "sim_slot_type": "{sim} 슬롯 유형",
        "sim_card_priority_title": "SIM 카드 우선순위",
        "sim_card_failover_title": "SIM 카드 페일오버",
        "scheduled_switch_preferred_sim_label": "예약된 선호 SIM 전환",
        "execution_time_label": "실행 시간",
        "select_active_sim_card": "활성 SIM 카드 선택",
        "no_sim_card": "SIM 카드 없음",
        "locked": "잠김",
        "sim_info_label": "{sim} 정보",
        "airplane_mode_tips": "비행기 모드가 켜져 있으며, 셀룰러 네트워크가 비활성화되었습니다.",
        "download_esim_config_tips": "인터넷에 연결하여 eSIM 구성 파일을 다운로드하십시오.",
        "unlock_pin_count_tips": "SIM 잠금 해제를 위해 PIN을 입력하세요. {count}회 남았습니다.",
        "network_type_tips": "더 빠른 속도를 위해 5G를 선택하거나(5G 신호 필요) 안정성을 위해 4G를 선택하세요.",
        "unavailable_tower_title": "사용 불가 타워",
        "lock_puk_tips": "{sim} 카드가 PIN 코드를 세 번 잘못 입력하여 잠겼습니다. 휴대폰에서 PUK 코드를 입력하여 잠금을 해제하세요.",
        "network_type_tips2": "타워/운영자를 잠그면 네트워크 유형이 고정되어 변경할 수 없습니다.",
        "lock_operator_fail_msg": "운영자 잠금 실패",
        "unlock_operator_fail_msg": "운영자 잠금 해제 실패"
    },
    "router_visual": {
        "wlan_client": "WLAN 클라이언트",
        "lan_Client": "LAN 클라이언트",
        "usb_client": "USB 클라이언트"
    },
    "sms": {
        "title": "문자 메시지",
        "send_sms": "메시지 전송",
        "receive": "수신하기",
        "all_read": "모든 '읽지 않은' SMS 메시지를 읽음으로 설정하기",
        "del_read": "읽은 메시지 삭제",
        "send": "보내기",
        "not_found_sms_modem": "이 모뎀은 문자 메시지를 지원하지 않습니다",
        "from": "출발",
        "to": "보내는 사람",
        "sent": "보냄",
        "sending": "보내는 중",
        "send_fail": "보내기 실패",
        "body": "문자 메시지 콘텐츠",
        "reply": "답글",
        "resend": "다시 보내기",
        "send_new": "새 메시지 생성",
        "resend_sms": "SMS 재전송",
        "reply_sms": "답글 달기",
        "send_modem": "모뎀(SIM)에서",
        "confirm_del": "삭제 확인",
        "invalid_dial_num": "잘못된 전화 번호",
        "international": "해외",
        "unknown": "알 수 없음",
        "no_sms": "No message",
        "detail": "SMS 세부 정보",
        "send_error_msg2": "알 수 없는 오류.",
        "send_error_msg4": "전송 시간 초과.",
        "send_error_msg6": "현재 네트워크 환경에서는 SMS 기능이 지원되지 않습니다.",
        "forward_smtp_title": "발신자 사서함(SMTP)",
        "forward_title": "SMS 전달하기",
        "forward_email_label": "Email",
        "forward_smtp_server_label": "SMTP 서버 주소",
        "forward_encryp_label": "암호화 방식",
        "forward_email_account_label": "사용자 이름",
        "forward_email_subject_label": "제목",
        "forward_email_list_title": "대상 Email",
        "forward_email_subject_tips": "SMS를 수신한 전화번호를 식별할 수 있도록 제목을 수정할 수 있습니다.",
        "forward_add_email_btn": "Email 추가",
        "forward_add_phone_btn": "전화 번호 추가",
        "forward_phone_tips": "라우터가 휴대폰으로 SMS를 전달하도록 하려면 모바일 네트워크를 사용할 수 있고 SMS 전송을 지원하는지 확인하세요.",
        "forward_no_encryp_label": "없음",
        "forward_tips": "순환을 방지하기 위해 여기에 지역 번호를 입력하면 SMS 전달이 허용되지 않습니다. 또한 모뎀이 SIM 카드 번호를 읽지 못하면 SMS 전달이 실행되지 않습니다.",
        "forward_email_title": "Email로 전달",
        "forward_sms_title": "SMS로 전달",
        "del_sms": "삭제",
        "recipient": "받는 사람",
        "national": "국가",
        "send_error_msg1": "모뎀이 감지되지 않았습니다.",
        "send_error_msg3": "전송 실패.",
        "send_error_msg5": "장치가 SMS 기능을 지원하지 않습니다.",
        "forward_email_tips": "SMS를 이메일로 전달하려면 먼저 발신자 이메일을 설정하세요. SMS가 전송될 이메일 주소입니다.",
        "received": "수신됨"
    },
    "modemmanage": {
        "title": "관리",
        "info": "모뎀 정보",
        "no_modem": "모뎀 장치를 찾을 수 없음",
        "at_command": "AT 명령어",
        "soft_reset": "소프트 재부팅",
        "port": "포트",
        "shortcut": "바로 가기",
        "send": "보내기",
        "cell_info": "휴대폰 정보",
        "copy": "복사",
        "refresh": "새로고침",
        "export_debug_info": "디버그 정보 내보내기",
        "hardware_reset": "하드 재부팅",
        "success_copy": "복사 완료",
        "reboot_sucess": "성공했습니다, $$$$ 초간 기다려주세요.",
        "unknown_command_msg": "알 수 없는 명령입니다",
        "sim_slot": "SIM 슬롯",
        "ims_tips": "IMS를 {status}하려면, 적용을 위해 장치를 리부팅하세요.",
        "disable": "비활성화",
        "enable": "활성화"
    },
    "menu_internet": "인터넷",
    "guide": {
        "configure_router_tip": "네트워크 가이드는 라우터를 구성하고 몇 분 안에 인터넷에 연결하는 데 도움을 줍니다.",
        "not_now": "지금은 아니요",
        "vpn_setup": "VPN 설정",
        "repeater_join_success_tip": "리피터 구성이 완료되었습니다.",
        "scan_nearby_wifi": "주변 Wi-Fi 네트워크 스캔 중",
        "connection_is_normal": "현재 네트워크 연결 유형은 {type}이며 네트워크 상태는 정상입니다.",
        "portal_login_mode_tips": "이 장치는 공공 핫스팟 로그인 모드에 있습니다. 수동으로 로그인 인증으로 이동할 수 있습니다.",
        "enter_login_mode_tips": "반복된 핫스팟을 통해 인터넷에 접속할 수 없습니다. 공공 핫스팟 로그인 모드로 들어가 문제를 해결해 보세요.",
        "click_to_enter_login_mode_tips": "공공 핫스팟 로그인 모드로 들어가려면 다음 버튼을 클릭하세요.",
        "restart_router_tip": "2.라우터를 재시작하세요.",
        "restart_main_router_tips": "主路由器重新启动。",
        "use_vpn_protect_privacy": "VPN을 사용하면 개인 정보를 보호할 수 있습니다. 지금 시도해보시겠습니까?",
        "successful_networking": "네트워킹 성공",
        "repeater_warning_connected_tips": "선택하신 네트워크 {failedSsid}가 연결에 실패했습니다. 저장된 네트워크 {connectedSsid}로 자동 전환되어 성공적으로 연결되었습니다.",
        "oops": "이런…",
        "step_one": "이런…",
        "step_two": "2단계",
        "four": "2단계",
        "wifi_scanning_tip": "Wi-Fi가 스캔 중입니다. 잠시만 기다려 주세요.",
        "wan_interface_detect_title": "WAN 인터페이스 감지",
        "scan_wifi_title": "주변 Wi-Fi 네트워크 스캔 중",
        "join": "加入",
        "phone_is_connected": "연결됨",
        "completed": "완료!",
        "attention_label": "주의!",
        "select_network_mode_tip": "네트워크 모드 선택",
        "lan_port_position_exception_tip": "LAN 포트가 네트워크 케이블을 감지했습니다. 케이블이 올바른 위치에 삽입되었는지 확인해 주십시오.",
        "ethernet_config_title": "이더넷 구성",
        "static_ip_config": "고정 IP 구성",
        "tethering_description_option": "USB 테더링을 통해 인터넷에 연결합니다.",
        "ethernet_description_option": "이더넷 케이블을 통해 인터넷에 연결합니다.",
        "repeater_description_option": "기존 Wi-Fi를 통해 인터넷에 연결합니다.",
        "cellular_description_option": "셀룰러를 통해 인터넷에 연결합니다.",
        "wait_window_pop_up": "'이 컴퓨터를 신뢰하시겠습니까?' 창이 나타날 때까지 기다린 후 '신뢰'를 클릭합니다.",
        "iphone_for_demonstration": "以iPhone12（iOS版本：17.5.1）为演示。请根据您手机的对应界面进行操作。",
        "connect_phone_or_pad_by_use_cable": "USB 케이블을 사용하여 iPhone/iPad를 라우터에 연결합니다.",
        "turn_on_cellular_and_tap_on_personal_hotspot": "설정으로 이동하여 셀룰러 데이터가 켜져 있는지 확인하고 개인용 핫스팟을 탭합니다.",
        "allow_other_join": "다른 기기의 연결을 허용합니다.",
        "android_for_demonstration": "USB 케이블을 사용하여 모바일 기기를 라우터에 연결합니다.",
        "connect_mobile_device_to_router": "USB 케이블을 사용하여 모바일 기기를 라우터에 연결합니다.",
        "enable_portable_hotspot_and_usb_tethering": "휴대용 핫스팟 및 USB 테더링을 활성화합니다.",
        "make_sure_cellular_is_turn_on": "모바일 기기의 셀룰러 데이터가 켜져 있는지 확인합니다.",
        "device_connected_and_network_normal": "{device}가 연결되었으며 네트워크가 정상입니다.",
        "network_loading_tip": "네트워크 가이드는 몇 분 만에 라우터를 구성하고 인터넷에 연결하는 데 도움을 줍니다.",
        "join_other_network": "다른 네트워크에 가입",
        "can_enjoy_the_internet": "이제 인터넷을 즐길 수 있습니다.",
        "support_email": "support@gl-inet.com",
        "enter_the_information": "정보 입력",
        "more_advanced_options": "더 고급 옵션은 메인 인터페이스를 사용하여 편집할 수 있습니다.",
        "failure_auto_obtain_data": "자동으로 데이터를 가져오지 못함",
        "can_choose_to_continue_the_process": "아래 과정을 수동으로 계속 진행하거나 모뎀을 리부팅할 수 있습니다.",
        "android_device": "안드로이드 기기",
        "step_three": "3단계",
        "repeater_configuration": "리피터 구성",
        "other": "기타",
        "operate_according_to_your_mobile_phone": "시스템 버전과 휴대폰 모델에 따라 인터페이스가 약간 다를 수 있습니다. 휴대폰에 해당하는 인터페이스에 따라 조작하십시오.",
        "wan_status_checking": "WAN 상태 확인 중입니다. 잠시만 기다려 주십시오.",
        "proto_connecting": "{proto} 연결 중",
        "unknow_device": "알 수 없는 기기",
        "password_is_wrong": "연결 실패. 비밀번호가 틀렸습니다. 다시 시도해 주세요.",
        "no_available_ap_tips": "현재 스캔된 사용 가능한 네트워크가 없습니다. {toDo} 할 수 있습니다.",
        "network_connection_feedback_title": "네트워크 연결 피드백",
        "repeater_warning_sub_tips": "현재 네트워크를 사용하고 싶지 않다면, 다른 네트워크를 선택하기 위해 뒤로 가세요.",
        "check_password_correct_tip": "광대역 계정 비밀번호가 정확한지 확인해 주세요. 비밀번호를 잊었다면, 운영자에게 연락할 수 있습니다.",
        "enter_broadband_password_placeholder": "광대역 비밀번호를 입력해 주세요",
        "pppoe_is_normal": "현재 네트워크 연결 유형은 PPPoE이며 네트워크 상태는 정상입니다.",
        "preset_static_ip": "고정 IP 모드 사용",
        "make_sure_wan_position_is_correct": "현재 WAN 포트가 LAN으로 사용되고 있습니다. 이더넷을 설정하려면 WAN 포트가 WAN으로 사용되고 있는지 확인해 주세요.",
        "manual_authentication_prompt": "수동 인증 프롬프트",
        "wait_for_four_second_to_login_tip": "기기가 공공 핫스팟용 로그인 모드에 있습니다. {num}초 후에 자동으로 로그인 페이지로 이동합니다.",
        "reboot_modem": "모뎀을 리부팅하세요",
        "ios_device": "iOS 기기",
        "enter_login_mode_for_public_hotspots_tip": "다음 버튼을 클릭하여 공공 핫스팟 로그인 모드로 들어갑니다.",
        "detecting_loading": "2. USB 케이블의 연결을 확인하고 다시 꽂거나 USB 케이블을 교체합니다.",
        "repeater_need_enable_auth_tips": "중계된 WiFi에 인증이 필요한 경우, 인증 모드를 활성화해 주십시오.",
        "fail_public_tips": "현재 네트워크에 연결할 수 없습니다. 다음 방법을 시도해 보십시오.",
        "restart_router_tips": "라우터를 재시작하세요.",
        "fail_contact_tips": "문제가 해결되지 않았다면, {addr}로 이메일을 보내실 수도 있습니다.",
        "enter_to_guide": {
            "tip": "여기를 클릭하여 초보자 가이드를 다시 입력하세요."
        },
        "tethering_device_connect_title": "테더링 장치 네트워크 연결",
        "exit_button": "여기를 클릭하여 초보자 가이드를 다시 입력하세요.",
        "tethering_connecting_note": "참고:",
        "finish": "완료",
        "proto_is_connected": "{proto}가 연결된 것으로 현재 감지되었습니다.",
        "wifi_not_found": "연결 실패. SSID 또는 비밀번호가 잘못되었습니다. 다시 시도해 주십시오.",
        "iphone": "아이폰",
        "repeater_concat_us": "3.문제가 해결되지 않은 경우, {supportEmail}로 이메일을 보내실 수도 있습니다.",
        "got_it": "알겠습니다",
        "tethering_connect_fail_title_start": "현재 네트워크 상태가 비정상입니다. 다음 방법을 시도해 보십시오.",
        "tethering_connected_description": "테더링 구성이 완료되었습니다. 이제 인터넷을 즐길 수 있습니다.",
        "network_connection_exception": "네트워크 연결 예외",
        "join_network": "네트워크 참여",
        "login_mode_for_public_hotspots": "공공 핫스팟용 로그인 모드",
        "available_networks": "사용 가능한 네트워크",
        "done": "완료",
        "no_cable_detected_tip": "케이블이 감지되지 않습니다. 네트워크 케이블을 WAN 포트에 연결해 주세요.",
        "enter_info_by_isp_tip": "ISP에서 제공하는 정보를 입력하세요.",
        "ethernet_connected_tip": "이더넷 구성이 완료되었습니다.",
        "select_proto_type_tip": "ISP가 인터넷 연결에 대한 정보를 제공하지 않는 경우 이 유형을 선택하세요.",
        "enter_to_guide_no_internet_tip": "네트워크 구성 방법을 모르시면 여기를 클릭하여 초보자 가이드로 들어갈 수 있습니다.",
        "network_guide_title": "네트워크 가이드",
        "suggest": "제안",
        "vpn_user_guide": "VPN 사용자 가이드",
        "network_detecting": "네트워킹 감지가 진행 중입니다, 잠시만 기다려 주세요.",
        "tethering_fail_restart_tips": "휴대폰과 라우터를 재시작하세요.",
        "tethering_fail_check_phone_tips": "휴대폰이 인증되었는지 확인하고 휴대폰 네트워크가 사용 가능한지 확인하십시오.",
        "tethering_fail_check_usb_tips": "USB 케이블의 연결 상태를 확인하고 케이블을 다시 꽂거나 교체하십시오.",
        "connect_success_public_tips": "{label}이(가) 연결되었으며 네트워크가 정상입니다.",
        "configuration_completed_tips": "{type} 구성이 완료되었습니다.",
        "fail_reboot_gateway_tips": "메인 게이트웨이를 리부팅하세요.",
        "contact_isp_tips": "ISP에 문의하여 도움을 받으십시오.",
        "cable_success_tips": "현재 네트워크 연결 유형은 {type}이며 네트워크 상태가 정상입니다.",
        "detecting_title": "检测中",
        "cable_no_wan_tips": "WAN 포트에 네트워크 케이블을 연결해 주세요.",
        "cable_no_wan_lan_tips": "LAN 포트에서 네트워크 케이블을 감지했습니다. 케이블이 올바른 위치에 삽입되었는지 확인해 주십시오.",
        "cable_wan_checking_tips": "WAN 상태를 확인 중입니다. 잠시만 기다려 주십시오.",
        "cable_pppoe_tips": "请输入您的ISP提供的信息。请确保宽带账户密码正确，如果忘记了，您可以联系您的运营商。",
        "cable_dhcp_tips": "ISP가 인터넷 연결에 대한 정보를 제공하지 않는 경우 이 유형을 선택하세요.",
        "use_static_btn": "사용 중인 정적 IP 모드",
        "cable_connecting_tips": "네트워킹 감지가 진행 중입니다, 잠시만 기다려 주세요.",
        "cable_manual_title": "获取数据失败",
        "cable_static_title": "고정 IP 설정",
        "cable_static_tips": "고급 옵션은 주 인터페이스를 사용하여 편집할 수 있습니다.",
        "cable_manual_tips": "모뎀을 수동으로 계속 조작하거나 리부팅할 수 있습니다.",
        "cable_config_title": "이더넷 구성",
        "cable_detect_title": "WAN 인터페이스 감지",
        "modem_fail_apn_tips": "수동으로 {do}를 시도해 보십시오. APN을 모르는 경우, 인터넷 서비스 제공업체(ISP)에 연락하십시오.",
        "modem_set_apn_btn": "设置正确的APN",
        "modem_fail_sim_tips": "SIM 카드가 사용 가능한지 확인하고 필요한 경우 교체하십시오.",
        "modem_sim_title": "SIM 카드를 삽입하십시오.",
        "modem_pin_title": "PIN 코드 입력",
        "modem_apn_title": "APN 설정",
        "modem_apn_tips": "ISP에 문의하여 올바른 APN을 확인하십시오.",
        "modem_dialling_tips": "다이얼 중입니다, 잠시 기다려 주십시오...",
        "modem_network_connecting_tips": "다이얼링이 성공했습니다. 네트워크 연결 중...",
        "modem_pin_tips": "SIM 카드의 PIN 코드는 3회 시도할 수 있습니다. 만약 3회 모두 잘못 입력된 경우, SIM 카드가 잠깁니다. 휴대폰을 사용하여 SIM 카드의 잠금을 해제해 주십시오. 이 SIM 카드의 PIN 코드를 모르는 경우, 인터넷 서비스 제공업체(ISP)에 문의하십시오.",
        "modem_sim_locked_tips": "PIN 코드를 3회 잘못 입력하여 SIM 카드가 잠겼습니다. 휴대폰을 통해 잠금을 해제해 주십시오.",
        "modem_pin_err_tips": "PIN 코드 {code}가 잘못되었습니다. 기회가 {count}번 더 있습니다.",
        "cable_enter_info_title": "To provide you with a translation, I need the specific text that you would like to have translated from English to Korean. Please provide the text you wish to translate, and I will assist you accordingly.",
        "modem_no_sim_reboot_tips": "SIM 카드를 다시 삽입했음에도 SIM 카드가 감지되지 않으면, 라우터를 재시작해 주세요.",
        "cable_fail_try_other_tips": "다른 {config}을 시도해 보세요.",
        "modem_auto_switching_tips": "SIM 카드 정보를 가져오는 중입니다, 잠시 기다려 주세요.",
        "cellular_detecting_title": "SIM 카드를 검사 중입니다",
        "cable_disabled_tips": "{feature}가 활성화되었습니다."
    },
    "traffic": {
        "no_saved_limit_tips": "데이터 사용량에 따라 SIM 카드를 잠그려면 \"전원을 끌 때 데이터 저장\" 스위치를 켜십시오.",
        "data_cap_amout_label": "데이터 사용량 제한",
        "data_used_label": "{sim} 데이터 사용량",
        "save_to_flash_label": "전원을 끌 때 데이터 저장",
        "save_to_flash_tips": "스위치를 켜면 장치의 전원이 꺼진 후에도 데이터를 저장할 수 있습니다.",
        "modify_data_used_tips": "데이터 통계는 참고용입니다. 실제 트래픽은 네트워크 운영자에 의해 결정되며, 네트워크 운영자가 제공하는 청구서에 표시됩니다.",
        "sim_limit_title": "{sim} 제한 설정",
        "modify_data_used_title": "{sim} 데이터 수정",
        "data_used_total_tips": "사용된 데이터는 현재 SIM 카드 슬롯의 데이터입니다.",
        "data_reset_period_label": "데이터 초기화 주기",
        "start_day_label": "시작 일",
        "start_hour_label": "시작 시간",
        "clear_warning_tips": "데이터 제한 구성을 수정한 후에는 데이터가 초기화됩니다. 데이터를 초기화하시겠습니까?",
        "second_month_label": "두 번째 달",
        "first_month_label": "첫 번째 달",
        "third_month_label": "세 번째 달",
        "sim_data_limit_common_tips": "데이터 사용량이 데이터 캡 제한을 초과하는 경우, 데이터 캡 제한 또는 데이터 사용량을 수동으로 수정해 주십시오.",
        "sim_data_limit_single_tips": "그렇지 않으면 SIM 카드가 비활성화됩니다.",
        "sim_data_limit_dual_tips": "그렇지 않으면 네트워크가 끊어질 수 있거나 SIM 카드가 {do}할 수 있습니다.",
        "over_limit_common_tips": "사용된 데이터가 데이터 캡 용량을 초과하였습니다. 데이터 캡 용량을 수정하거나 사용된 데이터를 수동으로 조정해 주십시오.",
        "sim_threshold_single_tips": "SIM 데이터 캡 용량이 설정되면, 데이터 사용량이 데이터 캡 용량을 초과하면 SIM이 비활성화됩니다.",
        "sim_threshold_dual_tips": "만약 {currentSim} 데이터 사용량 제한이 설정되어 있고 SIM 카드 슬롯 {handler}가 활성화되어 있다면, 데이터 사용량이 제한을 초과하면 {currentSim}에서 {otherSim}으로 자동 전환되며 {currentSim}은 비활성화됩니다.",
        "disabled_sim_auto_switch_tips": "SIM 카드는 데이터 제한에 도달했을 때 {handler}가 활성화되어 있지 않기 때문에 전환되지 않습니다. 그리고 데이터 제한에 도달하면 SIM 카드는 비활성화될 것입니다.",
        "enabled_sim_auto_switch_tips": "SIM 카드는 데이터 사용량이 제한에 도달하면 전환됩니다."
    },
    "cellular": {
        "tower_locked_label": "{sim} 타워 잠금",
        "operator_locked_label": "{sim} 운영자 잠금",
        "lock_operator_btn": "운영자 잠금",
        "lock_tower_disabled_tip": "현재 카드 슬롯이 운영자에게 잠겨 있기 때문에, 기지국에 잠긴 현재 카드 슬롯 기능이 비활성화되었습니다.",
        "scan_tower_warning_tips": "탑을 스캔하는 데 몇 분 정도 걸립니다. 계속하시겠습니까?",
        "lock_tower_tips": "기지국을 스캔하면 고품질 신호 소스를 신속하게 식별하여 안정적인 통신을 보장할 수 있습니다. 기지국에 연결하려면 통신사와 기기가 지원하는 주파수 대역을 일치시켜야 하며, 그렇지 않으면 통화에 영향을 줄 수 있습니다. 잠재적인 문제를 피하기 위해 기지국 정보를 확인해 주십시오.",
        "reflash_warning_msg": "페이지를 새로 고치지 마십시오.",
        "lock_operation_mode_label": "잠금 모드",
        "lock_operation_mode_tip": "운영자 잠금 기능은 세 가지 모드를 지원합니다: 사용 가능한 운영자 네트워크에 자동으로 연결, 특정 운영자에 수동으로 잠금 설정, 수동 잠금이 실패할 경우 사용 가능한 운영자 네트워크로 자동 전환.",
        "available_operator_title": "可用操作员",
        "scan_operator_warning_tips": "스캔하는 동안 몇 분 정도 걸리며, 이 기간 동안 임시로 네트워크 연결이 끊길 수 있습니다. 계속하시겠습니까?",
        "manual_select_operator_tips": "현재 운영자 목록은 참고용입니다. 수동 선택이 실패한 경우, 현재 SIM 카드에서 지원하는 운영자 목록을 참조하거나, 정확한 정보를 얻기 위해 운영자의 고객 서비스에 문의하십시오.",
        "lock_operator_fail_msg": "현재 운영자는 잠겨 있지만, 실제로는 카드 또는 운영자 제한으로 인해 사용할 수 없습니다. 네트워크를 복원하려면 수동 잠금 해제 작업을 수행해 주십시오.",
        "lock_operator_warning_tips": "잠긴 운영자가 셀룰러 설정의 대역 마스킹 또는 APN 매개변수와 일치하지 않으면 셀룰러 인터페이스는 인터넷에 연결할 수 없습니다.",
        "manual_auto_lock_operator_label": "수동-자동",
        "sim_info_title": "SIM 카드",
        "cell_info_title": "셀",
        "internet_info_title": "인터넷",
        "set_sim_config_warning_tips": "변경된 설정은 재다이얼을 초래할 것입니다.",
        "sim_settings_title": "SIM 카드 설정",
        "not_use_special_label": "未使用",
        "special_apns_label": "특수 APN 설정",
        "use_special_apn_warning_tips": "현재 선택하고 있는 특수 APN은 특정 휴대폰 카드에서만 사용할 수 있습니다. APN이 올바르게 설정되지 않으면 발신 이상, 네트워크 연결 실패 및 기타 통신 문제를 일으킬 수 있습니다. 귀하의 휴대폰 카드가 이 APN을 지원하는지 다시 한번 확인해 주십시오. 현재 APN으로 전환하시겠습니까?",
        "pin_code_tips": "PIN 코드 길이 4-8자리",
        "sim_switch_title": "SIM 카드 전환",
        "view_information_btn": "더 많은 정보 보기",
        "information_title": "셀룰러 정보",
        "special_apns_tips": "특별한 운영자가 제공하는 APN은 귀하의 SIM 카드의 실제 상황에 따라 선택하십시오.",
        "pin_code_last_unlock_tips": "SIM 카드가 잠겨 있으며 PIN 코드를 입력하여 잠금을 해제해야 합니다. 마지막 기회가 남아 있으니 잠금 해제를 시도해 보십시오. 만약 실패한다면 PUK 코드를 입력하여 휴대폰으로 잠금 해제를 해야 합니다.",
        "need_pin_code_tips": "SIM 카드가 잠겨 있으며 PIN 코드를 통해 잠금 해제해야 합니다. {count}번의 기회가 더 있습니다.",
        "pin_code_last_input_unlock_tips": "PIN 코드 {code}가 잘못되었습니다. 잠금을 해제할 마지막 기회가 남아 있습니다. 다시 실패하면 휴대폰을 사용하여 PUK 코드를 입력하여 잠금을 해제해야 합니다.",
        "manual_lock_operator_label": "手册",
        "ip_type_tips": "SIM 카드가 현재 IP 유형 설정을 지원하지 않거나, IPv6가 선택되었지만 {ipv6} 글로벌 스위치가 켜져 있지 않은 경우, 연결 이상이 발생할 수 있습니다.",
        "ip_type_label": "IP 유형",
        "initializing_tips": "모뎀이 초기화 중입니다……",
        "unavailable_operator_title": "사용 불가능한 운영자",
        "operator": "운영자",
        "tower": "타워",
        "network_type_conflicts_tips": "현재 SIM 카드 네트워크 유형은 {networkType}이며, {feature}의 네트워크 유형과 충돌합니다. 먼저 {settings}로 이동하여 네트워크 유형을 수정한 후 다시 잠금을 시도해 주세요.",
        "current_sim_badge_label": "활성: {sim}",
        "connection_failed": "연결 실패",
        "sim_operator": "{sim} 사업자",
        "sim_tower": "{sim} 타워",
        "sim_unlock": "{sim} 잠금 해제",
        "connecting_tips": "일부 SIM 카드에는 특정 APN을 요구하는 등 특별한 사용 제한이 있을 수 있습니다. SIM 카드가 등록되지 않는 경우 네트워크 사업자에게 문의하여 특별 제한 사항을 확인하고, SIM 카드에 사용 가능한 데이터가 있는지도 확인하십시오. {guide} 문제가 지속되면 {log}을(를) 생성하여 {addr}로 전송해 주십시오.",
        "download_log": "로그 다운로드",
        "lock_tower_fail_msg": "타워 잠금 실패",
        "unlock_tower_fail_msg": "타워 잠금 해제 실패",
        "modified_mtu_reboot_tips2": "MTU가 수정되었습니다. 적용을 위해 장치를 리부팅하십시오.",
        "modified_mtu_reboot_tips": "MTU가 수정된 경우, 적용을 위해 장치를 재부팅하십시오."
    },
    "sim": {
        "sender_label": "발신자"
    },
    "simo": {
        "sim_type_label": "SIM 카드 유형",
        "switch_to_label": "{slot}로 전환",
        "vsim_switch_to_physical_tips": "가상 SIM 카드(vSIM)에서 물리적 SIM 카드로 전환하게 됩니다. 인터넷에 연결하려면 물리적 SIM 카드를 기기 슬롯에 삽입해야 합니다. 물리적 SIM 카드가 삽입되었는지 확인해 주십시오.",
        "physical_switch_to_vsim_tips": "모듈의 물리적 SIM 카드에서 가상 SIM 카드(vSIM)로 전환하게 됩니다. simo 웹사이트에서 데이터 플랜을 구매하였는지 확인해야 합니다(장치에 있는 QR 코드를 스캔하여 구매하세요). 그런 다음 장치에서 물리적 SIM 카드를 제거할 수 있습니다.",
        "modem_name_label": "모뎀 이름"
    },
    "apn": {
        "enable_polling_label": "폴링 활성화",
        "polling_control_title": "APN 폴링 제어",
        "enable_polling_tips": "장치가 Verizon SIM 카드를 사용하고 이 기능이 활성화된 경우, 장치는 리부팅 후 최대 12분 동안 네트워크 연결이 정상화될 때까지 APN을 지속적으로 폴링합니다. 이 기능은 Verizon SIM 카드에서만 유효합니다."
    }
}
