{
    "cable": {
        "title": "以太网",
        "no_wan": "WAN 口检测不到网线，请插入网线。",
        "rm_wan_cable": "请拔出插入 WAN 口的网线。",
        "wan_been_lan": "WAN口已设置为LAN口模式，你可以将其设置回WAN口模式",
        "confirm_to_lan": "您确认要将 WAN 口做为 LAN 口使用吗？",
        "confirm_to_wan": "您确认要恢复 WAN 口功能吗？",
        "repeated": "已成功连接，不必重新连接",
        "pppoe_log": "PPPoE 连接日志",
        "setting": "有线网络配置",
        "dhcp_tips": "DHCP，由上级网络主机分配 IP。",
        "using_as_wan": "正在作为 WAN 口使用，$$$$切换至 LAN 口$$$$",
        "using_as_lan": "正在作为 LAN 口使用，$$$$切换至 WAN 口$$$$",
        "pppoe_vlanid_tips": "此配置项仅在供应商的 PPPoE 服务器需要接口使用标记特定 VLAN ID 的情况下需要输入。",
        "egderouter_mode_tips": "旁路由已启用。若要修改以太网配置，请先关闭$$$$旁路由$$$$。",
        "change_to_lan_check_tips": "请先拔出插入 WAN 口的网线。$$$$重新检测$$$$",
        "change_to_wan_tips": "LAN 口用作 WAN 口后，您将无法再通过网线连接到内网来访问管理员面板。请确保您的客户端可以连接 Wi-Fi。",
        "change_to_wan_tips2": "您可以按住设备上的重置按扭 4 秒钟来还原 LAN 口（不再作为 WAN 口）。"
    },
    "tethering": {
        "title": "热点共享",
        "device": "设备",
        "no_device_tips": "找不到热点共享设备，插入智能手机或 USB Modem 即可启动。"
    },
    "repeater": {
        "title": "中继",
        "known_net": "已知网络",
        "options": "中继选项",
        "no_tips": "中继未启用。",
        "allow_change": "允许切换至其它已保存网络",
        "allow_change_tips": "若此选项启用，在无法连接到当前连接的 Wi-Fi 时，路由器将尝试连接其它已保存的网络。",
        "antijam": "2.4G 网络强制使用 20MHz 带宽",
        "antijam_tips": "若此选项启用，设备将以降低连接速率为代价提升连接稳定性。",
        "lock_band": "频段选择",
        "lock_band_tips": "如果您手动选择了某个频段，路由器将无法扫描或连接到任何使用另一个频段的 Wi-Fi 。",
        "join_wifi": "加入 Wi-Fi",
        "join_title": "加入网络",
        "detail_title": "网络详情",
        "ssid": "名称",
        "encryption": "安全性",
        "identity": "用户名",
        "key": "密码",
        "remember": "保存网络",
        "lock_bssid": "锁定 BSSID",
        "set_static": "手动配置静态 IP",
        "available_wifi": "可用网络",
        "join_other": "加入其它网络",
        "change_wifi": "切换网络",
        "unlock": "自动",
        "antijam_tips_2": "该选项仅在中继 2.4G Wi-Fi 时生效。",
        "retry_connet_tips": "连接失败，稍后将重试……",
        "lock_bssid_tips": "如果启用该选项，路由器在切换到使用此 SSID 的网络时，只会尝试连接您所选的 BSSID 所对应的 AP。",
        "advanced_settings": "高级设置",
        "allow_dfs": "允许中继 DFS 信道",
        "allow_dfs_tips2": "若此选项禁用，路由器将不会连接到任意使用 DFS 信道的 Wi-Fi。",
        "allow_dfs_tips1": "若此选项启用，路由器中继 DFS 信道的 Wi-Fi 时，将跟随热点进行 DFS 信道规避。当该 Wi-Fi 可用时，路由器自身的 5GHz Wi-Fi 将使用 DFS 信道。否则，路由器自身的 5GHz Wi-Fi 将切换回非 DFS 信道。",
        "retry_disable_guest_tips": "尝试重新连接的过程中，路由器每隔一段时间会扫描周边 Wi-Fi，在扫描期间，您的访客网络 Wi-Fi 暂时被关闭。",
        "scan_disable_guest_tips": "扫描周边 Wi-Fi 信号期间，您的访客网络 Wi-Fi 将暂时被关闭，这需要 10 秒左右的时间，您确认要继续吗？",
        "fail_eap_key_tips": "用户名或密码不正确。",
        "fail_not_found_tips": "找不到该网络，请检查您输入的 SSID 和安全类型。",
        "fail_key_tips": "密码不正确。",
        "unusable_eap_tips": "此路由器不支持中继使用 EAP 的网络。",
        "fail_mac_tips": "路由器的 MAC 地址不能与 Wi-Fi 客户端相同，请$$$$修改克隆的 MAC$$$$或在该客户端上修改 MAC。",
        "scan_wifi_fail_dfs_tips": "设备正在进行 DFS 信道可用性检测，无法扫描周边 Wi-Fi。请等待检测结束。",
        "connet_dfs_tips": "路由器中继DFS信道的WiFi时，如果此WiFi可用，路由器将使用选择的DFS信道，需要注意的是，如果此WIFI不可用，将会切换信道，此时会导致通过WIFI连接的客户端短暂断开，有些设备会无感重连，有些需要手动重连。"
    },
    "modem": {
        "title": "蜂窝网络",
        "plug_in_tips": "未检测到 Modem，插入 USB Modem 以启动。",
        "manage": "管理",
        "name": "Modem 名称",
        "phone_num": "手机号码",
        "operator": "移动网络运营商",
        "signal": "信号",
        "upload": "上传",
        "download": "下载",
        "install_sim": "安装SIM卡",
        "install_sim_tips": "将您的 SIM 卡插入路由器的卡槽中，然后",
        "reboot_this": "重启 Modem",
        "port": "端口",
        "port_tips": "cdc-wcdm0 端口的速度更快，ttyUSBX 端口的兼容性更好。",
        "apn_tips": "部分 SIM 卡需要使用特定的 APN，如果您不清楚正确的 APN，请向您的运营商咨询。",
        "manually_tips": "手动输入",
        "ttl_tips": "部分运营商会通过检测 TTL 的值来判断 SIM 卡是否在路由器上使用，如果您的 SIM 卡无法在路由器上使用，您可以尝试将 TTL 设置为 64 和 128 以外的值（例如 65）。",
        "ttl_placeholder": "可选，默认 64",
        "pin": "PIN 码",
        "service": "服务",
        "dial_num": "号码",
        "authentication": "认证方式",
        "user_name": "用户名",
        "password": "密码",
        "sim_not_registered": "SIM卡未注册",
        "sim_lock": "SIM 卡已锁定，需要通过 PIN 码解锁。",
        "connect_fail_tips": "连接未成功，重试中……",
        "manual_setup": "手动设置",
        "auto_setup": "自动设置",
        "traffic": "流量统计",
        "traffic_tips": "流量统计结果仅供参考，实际流量以您的运营商提供账单的额度为准。",
        "reset_count": "清空统计",
        "clear_traffic": "禁用流量统计自动保存",
        "clear_traffic_tips": "若此选项启用，系统不会自动保存流量统计数据。",
        "not_compatible": "不兼容的 Modem",
        "no_sim_tips": "没有检测到您的 SIM 卡。请检查 SIM 卡插入的方向是否正确、接触是否良好。此 Modem 不支持热拔插 SIM 卡，如果您在开机后重新插入了 SIM 卡，请 $$$$重启 Modem$$$$ 或将您的路由器重启。",
        "connecting_tips": "部分 SIM 卡可能包含特殊的使用限制，比如需要使用特定的 APN 等。如果您的 SIM 卡不能注册，请向运营商咨询 SIM 卡是否有特殊限制。",
        "setting": "蜂窝网络配置",
        "current_sim_label": "使用的 SIM 卡",
        "current_config_title": "当前配置",
        "saved_config_title": "已保存的配置模板",
        "use_other_config_btn": "使用其它配置",
        "save_config_label": "保存配置",
        "main_slot_label": "首选 SIM 卡槽",
        "sim_failover_interval_label": "故障转移间隔",
        "timing_check_main_sim_tips": "若此选项启用，设备将会在指定时间尝试切换回首选 SIM 卡槽。以便在首选 SIM 卡槽的互联网连接可用时切换回使用它。",
        "check_main_sim_time_label": "切换时间",
        "sim_slot_switching_tips": "SIM 卡槽切换中……",
        "current_config_badge": "使用中",
        "copy_config_btn": "克隆并编辑",
        "sim_slot_setting_title": "SIM 卡槽配置",
        "auto_switch_label": "自动切换",
        "sim_profile_label": "SIM {index} 配置",
        "sim_no_profile_warning": "未选择配置文件，将进行自动配置。",
        "choose_other_profile_btn": "其它配置",
        "sim_failover_interval_tips": "若故障转移后仍无法联网，设备将切回首选 SIM 卡槽，并间隔一段时间后才会重新尝试故障转移。",
        "timing_check_main_sim_label": "定时检测首选卡槽状态",
        "choose_current_slot_label": "SIM 卡",
        "remove_profile_warning": "您确定要删除此配置模板吗？配置模板删除后无法恢复。",
        "set_detection_tips": "联网状态检测方式与$$$$多线负载页面$$$$中的配置一致。",
        "current_sim_badge_label": "正在使用 SIM {sim}",
        "data_roaming_label": "国际数据漫游",
        "enable_band_filter_label": "启用频段过滤",
        "band_masking_label": "屏蔽",
        "band_masking_tips": "“屏蔽”模式下，路由器将屏蔽下列频段。",
        "band_filter_mode_label": "过滤模式",
        "current_badge_label": "当前",
        "band_only_label": "仅使用",
        "band_only_tips": "“仅使用”模式下，路由器将仅使用下列频段，其他的频段将被屏蔽。",
        "band_only_warning": "请至少选择一个可使用的频段。",
        "excellent_singal_label": "极佳",
        "good_singal_label": "优良",
        "fair_singal_label": "一般",
        "poor_singal_label": "较差",
        "no_sim_tips2": "没有检测到您的 SIM 卡。请检查 SIM 卡插入的方向是否正确、接触是否良好。",
        "setting_sim_title": "SIM 卡使用的配置",
        "manage_profiles_btn": "管理配置模板",
        "save_as_profile_title": "另存为配置模板",
        "edit_profile_title": "修改配置模板",
        "select_profile_title": "选择配置模板",
        "sim_not_setup_label": "未设置",
        "add_new_profile_title": "添加新配置模板",
        "select_profile_desc": "你可以$$$$选择配置模板$$$$来将其中的内容复制到 SIM 卡使用的配置中。",
        "has_been_choose_profile_desc": "您已经复制了 {profileName} 中的内容。$$$$复制另一个$$$$",
        "name_already_exist_tips": "此名称已存在。",
        "history_signal_title": "历史信号记录",
        "lock_tower_title": "锁定基站",
        "locked_tower_tips": "如果被锁定的 tower 和 cellular 配置中的频段过滤或 APN 参数不匹配，cellular 接口将无法联网。",
        "device_may_not_b_tips": "Cellular 接口启用时，设备可能无法扫描到所有的基站。",
        "cellular_desc": "蜂窝网络接口将重新连接以切换到锁定的基站。",
        "scan_tower_msg": "这可能需要几分钟，请耐心等待。",
        "sim_tower_title": "SIM {sim} 基站",
        "available_tower_title": "可用基站",
        "tower_locked_tips": "基站已被锁定",
        "reboot_buildin_modem_warning": "你是否想要重启内置猫/调制解调器？",
        "reboot_buildin_modem_btn": "重启内置猫",
        "lte_plus_tips": "有些设备可能会将4G+显示为5G"
    },
    "router_visual": {
        "wlan_client": "无线客户端",
        "lan_Client": "LAN客户端"
    },
    "sms": {
        "title": "短信",
        "send_sms": "发送短信",
        "receive": "接收",
        "all_read": "全部已读",
        "del_read": "删除已读短信",
        "send": "发送",
        "not_found_sms_modem": "该 Modem 不支持短信功能",
        "from": "来自",
        "to": "发送给",
        "sent": "发送",
        "sending": "正在发送",
        "send_fail": "发送失败",
        "body": "短信内容",
        "reply": "回复",
        "resend": "重新发送",
        "del_sms": "删除",
        "send_new": "发送新短信",
        "resend_sms": "重新发送短信",
        "reply_sms": "回复短信",
        "recipient": "收件人",
        "send_modem": "发送 Modem",
        "confirm_del": "确认删除",
        "invalid_dial_num": "无效号码",
        "international": "国际",
        "national": "国内",
        "unknown": "未知",
        "no_sms": "没有信息",
        "detail": "短信详情",
        "send_error_msg1": "没有检测到 Modem。",
        "send_error_msg2": "未知错误。",
        "send_error_msg3": "发送失败。",
        "send_error_msg4": "发送超时。",
        "send_error_msg5": "当前设备不支持短信功能。",
        "send_error_msg6": "当前网络环境不支持短信功能。",
        "forward_email_tips": "如果您想转发短信到邮箱，请首先设置发件端邮箱，此邮箱用于发送短信到目标邮箱。",
        "forward_smtp_title": "发件端（SMTP）",
        "forward_title": "短信转发",
        "forward_email_label": "电子邮件",
        "forward_smtp_server_label": "SMTP 服务器地址",
        "forward_encryp_label": "加密方法",
        "forward_email_account_label": "用户名",
        "forward_email_subject_label": "主题",
        "forward_email_list_title": "目标邮箱",
        "forward_email_subject_tips": "您可以自定义主题，以便区分短信是由哪个号码收到的。",
        "forward_add_email_btn": "添加邮箱",
        "forward_add_phone_btn": "添加手机号码",
        "forward_phone_tips": "如果你想让路由器转发短信到您的手机上，请确保您的移动网络可用，且支持发送短信。",
        "forward_no_encryp_label": "不加密",
        "forward_tips": "为避免循环发送，此处填写本机号码时不会执行短信转发。此外，若 Modem 读不到您的 SIM 卡的号码，也不会执行短信转发。",
        "forward_email_title": "通过电子邮件转发",
        "forward_sms_title": "通过短信转发"
    },
    "modemmanage": {
        "title": "管理",
        "info": "Modem 信息",
        "no_modem": "找不到 Modem",
        "at_command": "AT指令",
        "soft_reset": "软重启",
        "port": "端口",
        "shortcut": "快捷方式",
        "send": "发送",
        "cell_info": "小区信息",
        "copy": "拷贝",
        "refresh": "刷新",
        "success_copy": "复制成功",
        "reboot_sucess": "处理成功，请等待 $$$$ 秒。",
        "export_debug_info": "导出历史信息",
        "hardware_reset": "硬重启"
    },
    "menu_internet": "互联网"
}
