{
    "cable": {
        "title": "有線",
        "no_wan": "WAN埠檢測不到網線，請插入網線。",
        "rm_wan_cable": "請移除WAN埠的網路線。",
        "wan_been_lan": "WAN埠已設置為LAN埠模式，你可以將其設回WAN埠模式",
        "confirm_to_lan": "你確認要把WAN埠作為LAN埠使用嗎？",
        "confirm_to_wan": "你確認要恢復WAN埠功能嗎？",
        "repeated": "已成功連接，不必重新連接",
        "using_as_lan": "正在作為LAN埠使用，$$$$切換至WAN埠$$$$",
        "using_as_wan": "正在作為WAN埠使用，$$$$切換至LAN埠$$$$",
        "pppoe_log": "PPPoE連接日誌",
        "setting": "有線網絡設置",
        "dhcp_tips": "由上級網絡主機分配IP。",
        "pppoe_vlanid_tips": "此配置項僅在供應商的 PPPoE 伺服器要求接口使用已標記的特定 VLAN ID 時才需要輸入。",
        "egderouter_mode_tips": "Drop-in gateway (旁路由) 已啟用。如果您想修改以太網設置，請先禁用 $$$$Drop-in Gateway$$$$。",
        "change_to_lan_check_tips": "請先拔出插入 WAN 口的網線。 $$$$重新檢測$$$$",
        "change_to_wan_tips": "LAN 口用作 WAN 口後，您將無法再通過網線連接到內網來訪問管理員面板。請確保您的客戶端可以連接 Wi-Fi。",
        "change_to_wan_tips2": "您可以按住設備上的重置按扭 4 秒鐘來還原 LAN 口（不再作為 WAN 口）。"
    },
    "tethering": {
        "title": "熱點分享",
        "device": "裝置",
        "no_device_tips": "找不到熱點分享設備，接入智能手機或USB無線上網數據機即可啟動。"
    },
    "repeater": {
        "title": "中繼",
        "known_net": "已知網路",
        "options": "中繼選項",
        "no_tips": "中繼已禁用。",
        "change_wifi": "切換網絡",
        "allow_change": "允許切換至其他已保存網絡",
        "allow_change_tips": "若啟用此選項，當無法連接到當前的Wi-Fi時，路由器將嘗試連接其他已保存的網絡。",
        "antijam_tips": "如果啟用此選項，設備將以降低連接速率為代價提高連接的穩定性。",
        "lock_band": "頻段選擇",
        "lock_band_tips": "若你手動選擇了某個頻段，路由器將不會掃瞄或連接到其他頻段的Wi-Fi。",
        "join_wifi": "加入 Wi-Fi",
        "join_title": "加入網絡",
        "detail_title": "網絡詳情",
        "available_wifi": "可用網絡",
        "join_other": "加入其他網絡",
        "ssid": "SSID",
        "encryption": "安全性",
        "identity": "用戶名稱",
        "key": "密碼",
        "remember": "保存網絡",
        "lock_bssid": "鎖定BSSID",
        "set_static": "手動設置靜態IP",
        "unlock": "自動",
        "retry_connet_tips": "連接失敗，稍後將重試…",
        "lock_bssid_tips": "若啟用此選項，路由器在切換到使用此 SSID 的網絡時，只會嘗試連接您所選的 BSSID 所對應的 AP。",
        "advanced_settings": "進階設置",
        "antijam": "2.4G 網絡強制使用20MHz 頻寬",
        "antijam_tips_2": "該選項僅在中繼 2.4G Wi-Fi 時生效。",
        "allow_dfs": "允許中繼 DFS 信道",
        "allow_dfs_tips1": "若此選項啟用，當路由器在任何 DFS 通道上重複 Wi-Fi 時，它將跟隨熱點進行 DFS 通道規避。 當此 Wi-Fi 可用時，路由器自身的 5GHz Wi-Fi 將使用 DFS 信道。 否則，路由器自身的 5GHz Wi-Fi 將切換回非 DFS 通道。",
        "allow_dfs_tips2": "如果禁用該選項，路由器將不會連接到任意使用 DFS 信道的 Wi-Fi。",
        "retry_disable_guest_tips": "嘗試重新連接的過程中，路由器每隔一段時間會掃描周邊 Wi-Fi，在掃描期間，你的訪客網絡 Wi-Fi 暫時被關閉。",
        "scan_disable_guest_tips": "掃描周邊 Wi-Fi 信號期間，您的訪客網絡 Wi-Fi 將暫時被關閉，這需要 10 秒左右的時間，你確認要繼續嗎？",
        "fail_not_found_tips": "找不到網絡，請檢查您輸入的 SSID 和安全類型。",
        "fail_eap_key_tips": "用戶名或密碼錯誤。",
        "fail_key_tips": "密碼錯誤。",
        "unusable_eap_tips": "此路由器不支持使用 EAP 的重複網絡。",
        "fail_mac_tips": "路由器的MAC不能與任何Wi-Fi客戶端相同，請$$$修改clone的MAC$$$$或修改該客戶端的MAC。"
    },
    "modem": {
        "title": "行動網絡",
        "plug_in_tips": "未檢測到無線上網數據機，接入USB 無線上網數據機以啟動。",
        "manage": "管理",
        "name": "數據機名稱",
        "phone_num": "手機號碼",
        "operator": "移動網絡營運商",
        "signal": "信號",
        "upload": "上載",
        "download": "下載",
        "install_sim": "安裝SIM卡",
        "install_sim_tips": "請插入你的SIM卡，然後",
        "reboot_this": "重啟數據機",
        "port": "通訊埠",
        "manually_tips": "手動輸入",
        "pin": "PIN碼",
        "service": "服務",
        "dial_num": "號碼",
        "authentication": "認證方式",
        "user_name": "用戶名稱",
        "password": "密碼",
        "no_sim_tips": "沒有檢測到您的 SIM 卡。請檢查 SIM 卡插入的方向是否正確、接觸是否良好。此 Modem 不支持熱拔插 SIM 卡，如果您在開機後重新插入了 SIM 卡，請 $$$$重啟數據機$$$$ 或將您的路由器重啟。",
        "sim_not_registered": "SIM卡未註冊",
        "sim_lock": "SIM卡已鎖定，需要通過PIN碼解鎖。",
        "connect_fail_tips": "連接失敗，重試中…",
        "auto_setup": "自動設置",
        "port_tips": "cdc-wcdm0 埠的速度更快，ttyUSBX 埠的兼容性更好。",
        "ttl_tips": "部分運營商會通過檢測 TTL 的值來判斷 SIM 卡是否在路由器上使用。如果您的 SIM 卡無法在路由器上使用，您可以嘗試將 TTL 設置為 64 和 128 以外的值（例如 65）。",
        "clear_traffic_tips": "若啟用此選項，系統將不會自動保存流量統計數據。",
        "connecting_tips": "有些SIM卡有特殊的使用限制，比如需要使用特定的APN。 如果您的 SIM 卡無法註冊，請向您的網絡運營商查詢您的 SIM 卡是否有任何特殊限制。",
        "apn_tips": "部分SIM卡需要特定的APN。如果你不清楚正確的APN，請向你的網絡營運商咨詢。",
        "ttl_placeholder": "可選，默認 64",
        "manual_setup": "手動設置",
        "setting": "行動網絡設置",
        "traffic_tips": "流量統計僅供參考； 實際流量由您的網絡運營商確定，並將顯示在您的網絡運營商提供的賬單上。",
        "traffic": "流量數據",
        "reset_count": "清除數據",
        "clear_traffic": "停用流量數據自動保存功能",
        "not_compatible": "不兼容的數據機",
        "band_filter_mode_label": "過濾模式",
        "band_masking_label": "屏蔽",
        "band_only_label": "僅使用",
        "band_only_tips": "“僅使用”模式下，路由器將僅使用下列頻段，其他的頻段將被屏蔽。",
        "band_masking_tips": "“屏蔽”模式下，路由器將屏蔽下列頻段。",
        "band_only_warning": "請至少選擇一個可使用的頻段。",
        "current_config_title": "當前配置",
        "enable_band_filter_label": "啟用頻段過濾",
        "set_detection_tips": "互聯網狀態檢測方式與$$$$多線負載頁面$$$$中的配置一致。",
        "data_roaming_label": "國際數據漫遊",
        "current_sim_badge_label": "當前：SIM {sim}",
        "excellent_singal_label": "極佳",
        "good_singal_label": "優良",
        "sim_slot_switching_tips": "SIM 卡槽切換中……",
        "current_sim_label": "啟動 SIM 卡",
        "saved_config_title": "已保存的配置模板",
        "use_other_config_btn": "使用其它配置",
        "current_config_badge": "使用中",
        "copy_config_btn": "複製並编辑",
        "fair_singal_label": "一般",
        "main_slot_label": "首選 SIM 卡槽",
        "poor_singal_label": "較差",
        "timing_check_main_sim_tips": "若此選項啟用，設備將會在指定時間嘗試切換回首選 SIM 卡槽。以便在首選 SIM 卡槽的互聯網連接可用時切換回使用它。",
        "check_main_sim_time_label": "切換時間",
        "choose_current_slot_label": "SIM卡",
        "current_badge_label": "當前",
        "save_config_label": "保存配置",
        "sim_slot_setting_title": "SIM 卡槽配置",
        "auto_switch_label": "自動切換",
        "sim_profile_label": "SIM {index} 配置",
        "sim_no_profile_warning": "未選擇配置文件，將進行自動配置。",
        "choose_other_profile_btn": "其他設置",
        "sim_failover_interval_label": "故障自動切換間隔",
        "sim_failover_interval_tips": "若故障自動切換後仍無法聯網，設備將切回首選 SIM 卡槽，並間隔一段時間後才會重新嘗試故障自動切換。",
        "timing_check_main_sim_label": "定時檢測首選卡槽狀態",
        "remove_profile_warning": "您確定要刪除此配置嗎？配置刪除後無法恢復。",
        "no_sim_tips2": "沒有檢測到您的 SIM 卡。請檢查 SIM 卡插入的方向是否正確、接觸是否良好。",
        "manage_profiles_btn": "管理配置模板",
        "setting_sim_title": "SIM 卡使用的配置",
        "save_as_profile_title": "另存爲配置模板",
        "edit_profile_title": "修改配置模板",
        "add_new_profile_title": "添加新配置模板",
        "select_profile_title": "選擇配置模板",
        "sim_not_setup_label": "未設置",
        "select_profile_desc": "妳可以$$$$選擇配置模板$$$$來將其中的內容複制到 SIM 卡使用的配置中。",
        "has_been_choose_profile_desc": "您已經復製了 {profileName} 中的內容。$$$$復製另一個$$$$",
        "name_already_exist_tips": "此名稱已存在",
        "device_may_not_b_tips": "啟用蜂窩接口時，設備可能無法掃描所有基站。",
        "history_signal_title": "歷史信號記錄",
        "lock_tower_title": "鎖定基站",
        "available_tower_title": "可用基站",
        "cellular_desc": "蜂窩接口將重新連接以切換到鎖定的基站。",
        "scan_tower_msg": "這可能需要幾分鐘的時間。請耐心等待。",
        "sim_tower_title": "SIM {sim} 基站",
        "locked_tower_tips": "如果被鎖定的 tower 和 cellular 配置中的頻段過濾或 APN 參數不匹配，cellular 接口將無法聯網。",
        "lte_plus_tips": "有些設備可能會將4G+顯示爲5G"
    },
    "router_visual": {
        "wlan_client": "無線網絡客戶端",
        "lan_Client": "LAN客戶端"
    },
    "modemmanage": {
        "title": "管理",
        "no_modem": "找不到無線上網數據機",
        "at_command": "AT指令",
        "port": "通訊埠",
        "shortcut": "捷徑",
        "send": "傳送",
        "cell_info": "小區信息",
        "copy": "複製",
        "refresh": "刷新",
        "success_copy": "複製成功",
        "info": "數據機信息",
        "soft_reset": "軟重啟",
        "reboot_sucess": "成功，請等待$$$$秒。",
        "export_debug_info": "匯出調試信息",
        "hardware_reset": "強制重啟"
    },
    "sms": {
        "title": "短訊",
        "send_sms": "傳送短訊",
        "receive": "接收",
        "all_read": "全部已讀",
        "del_read": "刪除已讀短信",
        "send": "傳送",
        "not_found_sms_modem": "此數據機不支持短信功能",
        "from": "來自",
        "to": "發送給",
        "sent": "已發送",
        "sending": "正在發送",
        "send_fail": "發送失敗",
        "body": "短信內容",
        "reply": "回覆",
        "resend": "重新發送",
        "del_sms": "刪除",
        "send_new": "發送新短信",
        "resend_sms": "重新發送短信",
        "reply_sms": "回复短信",
        "recipient": "收件人",
        "send_modem": "從數據機（SIM）",
        "confirm_del": "確認刪除",
        "invalid_dial_num": "無效號碼",
        "international": "國際",
        "national": "本地",
        "unknown": "未知",
        "no_sms": "没有訊息",
        "detail": "短信詳情",
        "send_error_msg4": "發送超時。",
        "send_error_msg1": "沒有檢測到數據機。",
        "send_error_msg2": "未知錯誤。",
        "send_error_msg3": "發送失敗。",
        "send_error_msg5": "當前設備不支持短信功能。",
        "send_error_msg6": "當前網絡環境不支持短信功能。",
        "forward_email_tips": "如果要轉發短信到郵箱，請先設置發件人郵箱。 這是發送 SMS 的電子郵件地址。",
        "forward_smtp_title": "發件人郵箱 (SMTP)",
        "forward_title": "短信轉發",
        "forward_email_label": "電子郵件",
        "forward_smtp_server_label": "SMTP 服務器地址",
        "forward_encryp_label": "加密方式",
        "forward_email_account_label": "用戶名",
        "forward_email_subject_label": "主題",
        "forward_email_list_title": "目標電子郵件",
        "forward_add_email_btn": "添加電子郵件",
        "forward_add_phone_btn": "添加電話號碼",
        "forward_no_encryp_label": "沒有",
        "forward_email_subject_tips": "您可以自定義主題，以便區分收到的短信的電話號碼。",
        "forward_phone_tips": "如果您希望使用路由器將短信轉發到您的手機，請確保您的移動網絡可用並支持發送短信。",
        "forward_tips": "為避免循環發送，此處填寫本機號碼時不會執行短信轉發。此外，若 Modem 讀不到您的 SIM 卡的號碼，也不會執行短信轉發。",
        "forward_email_title": "通過電子郵件轉發",
        "forward_sms_title": "通過短信轉發"
    },
    "menu_internet": "網絡"
}
