{
    "sdwan": {
        "no_device_tips": "若要使用此功能，您必須將設備添加到 {cloud} 中的某個虛擬網路內。",
        "download_data_title": "下行流量",
        "nodes_title": "網路拓撲圖",
        "upload_data_title": "上行流量",
        "real_time_data_title": "實時數據",
        "real_time_data_tips": "此處僅包括通過閘道的裝置數據，這可能與您的計費數據所報告的總量有所不同。",
        "device_tips": "此設備已被添加到虛擬網路 {network} 中。請轉到 {cloud} 修改設置。",
        "interface_title": "介面",
        "interface_tips": "您可以禁用特定介面加入連接聚合。",
        "get_start_tips": "點擊開始使用 AstroWarp！",
        "get_start_title": "啟用雲服務",
        "use_tips": "AstroWarp 是一款創新型的 VPN 平台，專為 GL 路由器而設計，它可以輕鬆設置網路出口節點和連接多個設備到虛擬網路中，從而能夠實現從任何地方進行輕鬆的遠端存取。",
        "enable_tips": "啟用AstroWarp時，無法使用 {feature}等功能。",
        "use_2b_tips": "AstroWarp是一款專為路由器設計的創新VPN平台，可輕鬆設置出口節點並在統一安全的網絡中連接多個遠程設備，實現隨時隨地的無縫遠程訪問。"
    },
    "menu_sdwan": "AstroWarp",
    "aw": {
        "go_to_aw_web_btn": "前往AstroWarp網站",
        "vaild_only_once_label": "僅限一次有效：",
        "first_get_start_step1_tips": "使用此路由器搭配AstroWarp，首先下载應用程序，然後連接到此路由器並通過它訪問互聯網。",
        "join_network_btn": "加入網路",
        "first_get_start_step2_tips": "點擊開始，我們將為您創建一個免費的AstroNet。此路由器將被設置為網絡出口。",
        "add_client_btn": "添加客戶端",
        "join_network_tips": "開始使用 AstroWarp 進行遠程辦公。您可以加入一個網路來使用它。或者您可以登錄 AstroWarp 網站以使用更多功能。",
        "data_usage_title": "數據用量",
        "link_life_time_label": "連結存活時間：",
        "usage_total_label": "使用量 / 总量",
        "use_as_internet_exit_tips": "此路由器已被設置為網際網路出口。",
        "use_internet_exit_label": "使用網際網路出口",
        "more_operation_tips": "所有客戶端和路由器使用網際網路出口通過此路由器訪問網際網路。如果需要修改配置，請登錄{page}。",
        "share_use_internet_exit_label": "使用網際網路出口",
        "to_download_app_btn": "點擊此處下載應用程式",
        "qrcode_use_tips": "使用應用程式掃描QR碼或輸入URL以訪問路由器，並使用其所屬的網路出口。",
        "share_more_operation_tips": "使用更多設置，請登錄{page}。",
        "go_to_aw_btn": "前往AstroWarp",
        "bind_not_self_tips": "在使用AstroWarp之前，請將您的帳戶綁定到Self視圖；目前不支持在組織或VAR視圖中使用。",
        "only_support_self_tips": "AstroWarp僅支援自我檢視。",
        "operate_config_tips": "如果您需要修改配置，请登录{page}。",
        "exit_node_label": "出口節點",
        "add_client_limit_tips": "接入此路由器的客戶端數量已達上限。請訪問 AstroWarp 以升級您的網路套餐。",
        "add_router_limit_tips": "此網絡中接入的路由器數量已達上限。請前往AstroWarp編輯您的網絡。",
        "network_plan_expired_tips": "該網路已過期。請前往 AstroWarp 升級/續訂您的網路方案。",
        "unlimit_label": "無限制",
        "get_start_common_tips": "開始使用居家辦公方案，您可透過此路由器作為網路出口，無論身處何地都能使用其WAN IP存取網際網路及伺服器。",
        "web_title": "AstroWarp 管理面板",
        "get_start_has_networks_tips": "點擊按鈕，選擇一個出口節點路由器來使用，並通過它訪問互聯網和伺服器。",
        "first_get_start_download_app_tips": "1. 在您的手機或電腦上下載AstroWarp應用程式。",
        "first_get_start_use_app_tips": "3. 使用應用程式掃描或在出口節點頁面輸入代碼。",
        "get_start_btn": "開始使用",
        "install_app_title": "安裝應用程式以開始使用",
        "first_get_start_connected_tips": "4. 您已連接！",
        "first_get_start_click_tips": "2. 點擊按鈕將此路由器設為您的網路出口節點。",
        "scan_qrcode_tips": "掃描二維碼或在AstroWarp應用中輸入代碼，即可通過此路由器安全存取網際網路及伺服器。",
        "copy_link_btn": "複製代碼",
        "download_app_titile": "下載應用程式",
        "get_start_step_title": "开始使用",
        "no_available_node_tips": "您的帳戶下沒有可用的出口節點。請點擊AstroWarp按鈕前往管理面板配置您的出口節點。",
        "confirm_node_tips": "確認已開始安全地透過出口節點存取網際網路",
        "select_node_tips": "選擇一個出口節點以安全地透過它存取網際網路。",
        "start_btn": "啟動",
        "start_process_checking_tips": "正在檢查網路狀態...",
        "start_process_connecting_tips": "正在連接伺服器...",
        "start_process_starting_tips": "正在啟動AstroWarp服務...",
        "start_process_success_tips": "設定成功！",
        "start_process_error_common_tips": "連接失敗。發生未知錯誤。請檢查您的網路或稍後再試。如果問題持續存在，請聯繫支援或提交意見回饋。",
        "exit_network_btn": "退出 AstroWrap",
        "exit_ip_label": "出口 IP",
        "exit_network_tips": "退出將移除所有已新增的客戶端。若要再次使用Astrowrap，您需重新新增這些客戶端。確定要繼續執行嗎？",
        "exit_btn": "退出"
    },
    "aw_err": {
        "not_joined_network_msg": "未加入此網路。"
    }
}
