{
    "dns": {
        "edit_host_btn": "호스트 편집",
        "desc": "사용자 지정 DNS 서버를 설정하면 모든 도메인 이름은 이더넷, 리피터, 셀룰러, 테더링 또는 VPN 구성 DNS 서버에서 가져온 것이 아니라 여기에서 설정한 DNS 서버를 통해 확인됩니다.",
        "rebinding_label": "DNS 리바인딩 공격 차단",
        "rebinding_tips": "이 옵션을 켜면 비공개 DNS 조회에 실패할 수 있습니다. 네트워크에 캡티브 포털이 있는 경우 이 옵션을 비활성화하세요.",
        "override_label": "모든 클라이언트의 DNS 설정 덮어쓰기",
        "override_tips": "활성화하면 라우터가 모든 클라이언트에 대해 암호화되지 않은 DNS 설정을 재정의합니다.",
        "set_dns_server_title": "DNS 서버 설정",
        "mode": "모드",
        "proxy_addr_label": "프록시 서버 주소",
        "encryption_type_label": "암호화 유형",
        "v1_tips": "라우터는 버전 v1 DNS를 사용합니다. 모든 암호화된 DNS 서버가 지원되는 것은 아닙니다.",
        "select_server_btn": "서버 선택",
        "select_nodnssec_label": "DNSSEC 없음",
        "host_tips": "클라이언트의 요청은 처음에는 호스트에 작성한 정적 DNS 규칙을 사용하여 해결됩니다.",
        "form_wan_label": "이더넷에서 DNS",
        "adguardhome_in_use_tips": "AdGuard Home이 활성화된 경우, 라우터는 AdGuard Home에서 제공하는 DNS 서버를 사용해야 하며 DNS 서버를 사용자 지정할 수 없습니다.",
        "server": "서버",
        "server_tips": "최대 8개의 서버를 선택할 수 있습니다. 라우터는 이 중 가장 빠른 서버를 자동으로 선택합니다.",
        "at_least_one_server_tips": "서버를 하나 이상 선택",
        "choose_server_title": "DNS 서버 선택",
        "select_all_label": "모두",
        "select_log_label": "기록",
        "select_nolog_label": "기록 없음",
        "select_filter_label": "필터",
        "select_nofilter_label": "필터 없음",
        "auto_get_label": "자동화",
        "choose_encryption_label": "암호화된 DNS",
        "manual_label": "수동 DNS",
        "set_proxy_label": "DNS 프록시",
        "form_wwan_label": "리피터에서 DNS",
        "form_tethering_label": "테더링에서 DNS",
        "form_modem_label": "셀룰러에서 DNS",
        "form_ovpn_label": "OpenVPN에서 DNS",
        "form_wg_label": "WireGuard에서 DNS",
        "provider": "DNS 제공업체",
        "server_warning_tips": "서버가 만료되었습니다.",
        "form_interface_label": "{interface}에서 DNS",
        "bark_enable_override_tips": "Bark는 인터넷으로 전송되는 클라이언트의 거의 모든 DNS 요청을 차단합니다. Bark가 작동하는 동안 이 옵션을 활성화하면 클라이언트가 인터넷에 액세스하지 못할 수 있습니다."
    }
}
