{
    "dns": {
        "form_ovpn_label": "",
        "proxy_addr_label": "",
        "at_least_one_server_tips": "",
        "choose_encryption_label": "",
        "provider": "",
        "set_dns_server_title": "",
        "choose_server_title": "",
        "select_nodnssec_label": "",
        "select_log_label": "",
        "select_filter_label": "",
        "form_wan_label": "",
        "form_tethering_label": "",
        "manual_label": "",
        "rebinding_tips": "",
        "host_tips": "",
        "server_tips": "",
        "rebinding_label": "",
        "form_interface_label": "",
        "set_proxy_label": ""
    }
}
